basic_projects/11_3to8_Decoder/Decoder_3to8_behav.v
module Decoder_3to8_behav(input [2:0] i, output reg [7:0] y);



always @(*) begin
    y=8'b00000000;
case(i)

3'b000: y[0]=1;
3'b001: y[1]=1;
3'b010: y[2]=1;
3'b011: y[3]=1;
3'b100: y[4]=1;
3'b101: y[5]=1;
3'b110: y[6]=1;
3'b111: y[7]=1;
default: y=8'bxxxxxxxx;
endcase

end
    
    
  
endmodule

basic_projects/11_3to8_Decoder/testbench.v
`timescale 1ns/1ns

module testbench;
reg [2:0] i;
wire [7:0] y;
integer ip;
Decoder_3to8_behav behav(i,y);
    initial begin

$dumpfile("Decoder_3to8.vcd");
$dumpvars(0,testbench);


        for(ip=0;ip<8;ip=ip+1)
        begin
         
         {i[2],i[1],i[0]}=ip[2:0];
         #10;
         $display("i[2]=%b,i[1]=%b,i[0]=%b,y=%b",i[2],i[1],i[0],y);

        end
        $finish;
    end


endmodule

basic_projects/11_3to8_Decoder/Decoder_3to8.vcd
$date
	Tue Jun 17 15:31:52 2025
$end
$version
	Icarus Verilog
$end
$timescale
	1ns
$end
$scope module testbench $end
$var wire 8 ! y [7:0] $end
$var reg 3 " i [2:0] $end
$var integer 32 # ip [31:0] $end
$scope module behav $end
$var wire 3 $ i [2:0] $end
$var reg 8 % y [7:0] $end
$upscope $end
$upscope $end
$enddefinitions $end
#0
$dumpvars
b1 %
b0 $
b0 #
b0 "
b1 !
$end
#10
b10 %
b10 !
b1 "
b1 $
b1 #
#20
b100 %
b100 !
b10 "
b10 $
b10 #
#30
b1000 %
b1000 !
b11 "
b11 $
b11 #
#40
b10000 %
b10000 !
b100 "
b100 $
b100 #
#50
b100000 %
b100000 !
b101 "
b101 $
b101 #
#60
b1000000 %
b1000000 !
b110 "
b110 $
b110 #
#70
b10000000 %
b10000000 !
b111 "
b111 $
b111 #
#80
b1000 #
