basic_projects/14_BCDto7-Segment_Decoder/BCDto7_Segment_Decoder_behav.v
module BCDto7_Segment_Decoder_behav (input [3:0] k,output reg a,b,c,d,e,f,g);

always @(*) begin
  
case(k)

 4'b0000: begin a=1; b=1; c=1; d=1; e=1; f=1; g=0; end // 0
        4'b0001: begin a=0; b=1; c=1; d=0; e=0; f=0; g=0; end // 1
        4'b0010: begin a=1; b=1; c=0; d=1; e=1; f=0; g=1; end // 2
        4'b0011: begin a=1; b=1; c=1; d=1; e=0; f=0; g=1; end // 3
        4'b0100: begin a=0; b=1; c=1; d=0; e=0; f=1; g=1; end // 4
        4'b0101: begin a=1; b=0; c=1; d=1; e=0; f=1; g=1; end // 5
        4'b0110: begin a=1; b=0; c=1; d=1; e=1; f=1; g=1; end // 6
        4'b0111: begin a=1; b=1; c=1; d=0; e=0; f=0; g=0; end // 7
        4'b1000: begin a=1; b=1; c=1; d=1; e=1; f=1; g=1; end // 8
        4'b1001: begin a=1; b=1; c=1; d=1; e=0; f=1; g=1; end // 9
        default: begin a=0; b=0; c=0; d=0; e=0; f=0; g=0; end  // blank


endcase

end



    
  
endmodule

basic_projects/14_BCDto7-Segment_Decoder/testbench.v
`timescale 1ns/1ns

module testbench;

reg [3:0] k;
wire a, b, c, d, e, f, g;

integer i;

BCDto7_Segment_Decoder_behav behav(k, a, b, c, d, e, f, g);

initial begin
    $dumpfile("BCDto7-Segment_Decoder.vcd");
    $dumpvars(0, testbench);
    $display(" BCD | a b c d e f g | 7-segment");
    $display("----------------------------------");
    for (i = 0; i < 16; i = i + 1) begin
        k = i[3:0];
        #10;
        if (i < 10) begin
            $display(" %b%b%b%b | %b %b %b %b %b %b %b |   %0d",
                     k[3], k[2], k[1], k[0],
                     a, b, c, d, e, f, g,
                     i);
        end else begin
            $display(" %b%b%b%b | %b %b %b %b %b %b %b |",
                     k[3], k[2], k[1], k[0],
                     a, b, c, d, e, f, g);
        end
    end
    $finish;
end

endmodule

basic_projects/14_BCDto7-Segment_Decoder/BCDto7-Segment_Decoder.vcd
$date
	Tue Jun 17 19:40:10 2025
$end
$version
	Icarus Verilog
$end
$timescale
	1ns
$end
$scope module testbench $end
$var wire 1 ! a $end
$var wire 1 " b $end
$var wire 1 # c $end
$var wire 1 $ d $end
$var wire 1 % e $end
$var wire 1 & f $end
$var wire 1 ' g $end
$var integer 32 ( i [31:0] $end
$var reg 4 ) k [3:0] $end
$scope module behav $end
$var wire 4 * k [3:0] $end
$var reg 1 + a $end
$var reg 1 , b $end
$var reg 1 - c $end
$var reg 1 . d $end
$var reg 1 / e $end
$var reg 1 0 f $end
$var reg 1 1 g $end
$upscope $end
$upscope $end
$enddefinitions $end
#0
$dumpvars
01
10
1/
1.
1-
1,
1+
b0 *
b0 )
b0 (
0'
1&
1%
1$
1#
1"
1!
$end
#10
00
0&
0/
0%
0.
0$
0+
0!
b1 )
b1 *
b1 (
#20
11
1'
1/
1%
1.
1$
0-
0#
1+
1!
b10 )
b10 *
b10 (
#30
0/
0%
1-
1#
b11 )
b11 *
b11 (
#40
10
1&
0.
0$
0+
0!
b100 )
b100 *
b100 (
#50
1.
1$
0,
0"
1+
1!
b101 )
b101 *
b101 (
#60
1/
1%
b110 )
b110 *
b110 (
#70
01
0'
00
0&
0/
0%
0.
0$
1,
1"
b111 )
b111 *
b111 (
#80
11
1'
10
1&
1/
1%
1.
1$
b1000 )
b1000 *
b1000 (
#90
0/
0%
b1001 )
b1001 *
b1001 (
#100
01
0'
00
0&
0.
0$
0-
0#
0,
0"
0+
0!
b1010 )
b1010 *
b1010 (
#110
b1011 )
b1011 *
b1011 (
#120
b1100 )
b1100 *
b1100 (
#130
b1101 )
b1101 *
b1101 (
#140
b1110 )
b1110 *
b1110 (
#150
b1111 )
b1111 *
b1111 (
#160
b10000 (
