basic_projects/02_full_adder/full_adder_gatelevel.v
module full_adder_gatelevel(input x,y,z, output sum,carry);
wire w1,w2,w3;
//summation
xor g1(w1,x,y),
    g2(sum,z,w1);
//for carry
and g3(w2,x,y),
    g4(w3,z,w1);
//to get final carry
or g5(carry,w2,w3);
endmodule

basic_projects/02_full_adder/full_adder_behaviourlevel.v
module full_adder_behaviourlevel(input x,y,z, output sum,carry);

assign sum = x^y^z;
assign carry = (x&y) | (y&z) | (x&z);


endmodule

basic_projects/02_full_adder/testbench.v
module testbench;

reg x,y,z;
wire sum_gate,sum_behav,carry_gate,carry_behav;

integer i;

full_adder_behaviourlevel behav(.x(x),.y(y),.z(z),.sum(sum_behav),.carry(carry_behav));
full_adder_gatelevel gate(.x(x),.y(y),.z(z),.sum(sum_gate),.carry(carry_gate));

initial begin
$dumpfile("Full_adder.vcd");
$dumpvars(0, testbench);

for(i=0;i<8;i=i+1)
begin 
{x,y,z} = i[2:0];

    #5;
end
$finish;
 end

 initial begin 

$monitor($time,"x=%b,y=%b,z%b,sum_behav=%b,carry_behav=%b,sum_gate=%b,carry_gate=%b", x,y,z,sum_behav,carry_behav,sum_gate,carry_gate);

 end
endmodule

basic_projects/02_full_adder/Full_adder.vcd
$date
	Mon Jun 16 12:06:51 2025
$end
$version
	Icarus Verilog
$end
$timescale
	1s
$end
$scope module testbench $end
$var wire 1 ! carry_behav $end
$var wire 1 " carry_gate $end
$var wire 1 # sum_behav $end
$var wire 1 $ sum_gate $end
$var integer 32 % i [31:0] $end
$var reg 1 & x $end
$var reg 1 ' y $end
$var reg 1 ( z $end
$scope module behav $end
$var wire 1 ! carry $end
$var wire 1 # sum $end
$var wire 1 ) x $end
$var wire 1 * y $end
$var wire 1 + z $end
$upscope $end
$scope module gate $end
$var wire 1 " carry $end
$var wire 1 $ sum $end
$var wire 1 , w1 $end
$var wire 1 - w2 $end
$var wire 1 . w3 $end
$var wire 1 ) x $end
$var wire 1 * y $end
$var wire 1 + z $end
$upscope $end
$upscope $end
$enddefinitions $end
#0
$dumpvars
0.
0-
0,
0+
0*
0)
0(
0'
0&
b0 %
0$
0#
0"
0!
$end
#5
1#
1$
1(
1+
b1 %
#10
1,
1#
1$
1'
1*
0(
0+
b10 %
#15
1!
1"
0#
0$
1.
1(
1+
b11 %
#20
0!
0"
1#
1$
0.
1&
1)
0'
0*
0(
0+
b100 %
#25
1!
1"
0#
0$
1.
1(
1+
b101 %
#30
1!
0,
1-
0#
0$
0.
1'
1*
0(
0+
b110 %
#35
1#
1$
1(
1+
b111 %
#40
b1000 %
