basic_projects/13_4-Bit-Data_Comparator/4_Bit_Data_Comparator_behav.v
module Data_Comparator_4_Bit_behav(input [3:0] a,b, output reg a_g_b,a_e_b,b_g_a);


always @(*) begin
      a_g_b = 0;
    a_e_b = 0;
    b_g_a = 0;
if(a>b)
a_g_b = 1;
else if(a==b) 
a_e_b = 1;
else
b_g_a = 1;

end
    
    
  
endmodule

basic_projects/13_4-Bit-Data_Comparator/testbench.v
`timescale 1ns/1ns

module testbench;
reg  [3:0] a, b;
wire a_g_b,a_e_b,b_g_a;
integer i;
Data_Comparator_4_Bit_behav behav(a,b,a_g_b,a_e_b,b_g_a);
    initial begin

$dumpfile("Data_Comparator_4_Bit.vcd");
$dumpvars(0,testbench);
$display(" a | b |  a > b  |  a = b  |  a < b  |");
for(i=0;i<256;i=i+1)begin
    {a,b}=i[7:0];
    #10;
    $display(" %b | %b |  %b  |  %b  |  %b  |",  a, b, a_g_b, a_e_b, b_g_a );
end
        $finish;
    end


endmodule

basic_projects/13_4-Bit-Data_Comparator/Data_Comparator_4_Bit.vcd
$date
	Tue Jun 17 18:35:10 2025
$end
$version
	Icarus Verilog
$end
$timescale
	1ns
$end
$scope module testbench $end
$var wire 1 ! a_e_b $end
$var wire 1 " a_g_b $end
$var wire 1 # b_g_a $end
$var reg 4 $ a [3:0] $end
$var reg 4 % b [3:0] $end
$var integer 32 & i [31:0] $end
$scope module behav $end
$var wire 4 ' a [3:0] $end
$var wire 4 ( b [3:0] $end
$var reg 1 ) a_e_b $end
$var reg 1 * a_g_b $end
$var reg 1 + b_g_a $end
$upscope $end
$upscope $end
$enddefinitions $end
#0
$dumpvars
0+
0*
1)
b0 (
b0 '
b0 &
b0 %
b0 $
0#
0"
1!
$end
#10
1+
1#
0)
0!
b1 %
b1 (
b1 &
#20
1+
1#
b10 %
b10 (
b10 &
#30
1+
1#
b11 %
b11 (
b11 &
#40
1+
1#
b100 %
b100 (
b100 &
#50
1+
1#
b101 %
b101 (
b101 &
#60
1+
1#
b110 %
b110 (
b110 &
#70
1+
1#
b111 %
b111 (
b111 &
#80
1+
1#
b1000 %
b1000 (
b1000 &
#90
1+
1#
b1001 %
b1001 (
b1001 &
#100
1+
1#
b1010 %
b1010 (
b1010 &
#110
1+
1#
b1011 %
b1011 (
b1011 &
#120
1+
1#
b1100 %
b1100 (
b1100 &
#130
1+
1#
b1101 %
b1101 (
b1101 &
#140
1+
1#
b1110 %
b1110 (
b1110 &
#150
1+
1#
b1111 %
b1111 (
b1111 &
#160
1*
1"
0+
0#
b1 $
b1 '
b0 %
b0 (
b10000 &
#170
1)
1!
0*
0"
b1 %
b1 (
b10001 &
#180
1+
1#
0)
0!
b10 %
b10 (
b10010 &
#190
1+
1#
b11 %
b11 (
b10011 &
#200
1+
1#
b100 %
b100 (
b10100 &
#210
1+
1#
b101 %
b101 (
b10101 &
#220
1+
1#
b110 %
b110 (
b10110 &
#230
1+
1#
b111 %
b111 (
b10111 &
#240
1+
1#
b1000 %
b1000 (
b11000 &
#250
1+
1#
b1001 %
b1001 (
b11001 &
#260
1+
1#
b1010 %
b1010 (
b11010 &
#270
1+
1#
b1011 %
b1011 (
b11011 &
#280
1+
1#
b1100 %
b1100 (
b11100 &
#290
1+
1#
b1101 %
b1101 (
b11101 &
#300
1+
1#
b1110 %
b1110 (
b11110 &
#310
1+
1#
b1111 %
b1111 (
b11111 &
#320
1*
1"
0+
0#
b10 $
b10 '
b0 %
b0 (
b100000 &
#330
1*
1"
b1 %
b1 (
b100001 &
#340
1)
1!
0*
0"
b10 %
b10 (
b100010 &
#350
1+
1#
0)
0!
b11 %
b11 (
b100011 &
#360
1+
1#
b100 %
b100 (
b100100 &
#370
1+
1#
b101 %
b101 (
b100101 &
#380
1+
1#
b110 %
b110 (
b100110 &
#390
1+
1#
b111 %
b111 (
b100111 &
#400
1+
1#
b1000 %
b1000 (
b101000 &
#410
1+
1#
b1001 %
b1001 (
b101001 &
#420
1+
1#
b1010 %
b1010 (
b101010 &
#430
1+
1#
b1011 %
b1011 (
b101011 &
#440
1+
1#
b1100 %
b1100 (
b101100 &
#450
1+
1#
b1101 %
b1101 (
b101101 &
#460
1+
1#
b1110 %
b1110 (
b101110 &
#470
1+
1#
b1111 %
b1111 (
b101111 &
#480
1*
1"
0+
0#
b11 $
b11 '
b0 %
b0 (
b110000 &
#490
1*
1"
b1 %
b1 (
b110001 &
#500
1*
1"
b10 %
b10 (
b110010 &
#510
1)
1!
0*
0"
b11 %
b11 (
b110011 &
#520
1+
1#
0)
0!
b100 %
b100 (
b110100 &
#530
1+
1#
b101 %
b101 (
b110101 &
#540
1+
1#
b110 %
b110 (
b110110 &
#550
1+
1#
b111 %
b111 (
b110111 &
#560
1+
1#
b1000 %
b1000 (
b111000 &
#570
1+
1#
b1001 %
b1001 (
b111001 &
#580
1+
1#
b1010 %
b1010 (
b111010 &
#590
1+
1#
b1011 %
b1011 (
b111011 &
#600
1+
1#
b1100 %
b1100 (
b111100 &
#610
1+
1#
b1101 %
b1101 (
b111101 &
#620
1+
1#
b1110 %
b1110 (
b111110 &
#630
1+
1#
b1111 %
b1111 (
b111111 &
#640
1*
1"
0+
0#
b100 $
b100 '
b0 %
b0 (
b1000000 &
#650
1*
1"
b1 %
b1 (
b1000001 &
#660
1*
1"
b10 %
b10 (
b1000010 &
#670
1*
1"
b11 %
b11 (
b1000011 &
#680
1)
1!
0*
0"
b100 %
b100 (
b1000100 &
#690
1+
1#
0)
0!
b101 %
b101 (
b1000101 &
#700
1+
1#
b110 %
b110 (
b1000110 &
#710
1+
1#
b111 %
b111 (
b1000111 &
#720
1+
1#
b1000 %
b1000 (
b1001000 &
#730
1+
1#
b1001 %
b1001 (
b1001001 &
#740
1+
1#
b1010 %
b1010 (
b1001010 &
#750
1+
1#
b1011 %
b1011 (
b1001011 &
#760
1+
1#
b1100 %
b1100 (
b1001100 &
#770
1+
1#
b1101 %
b1101 (
b1001101 &
#780
1+
1#
b1110 %
b1110 (
b1001110 &
#790
1+
1#
b1111 %
b1111 (
b1001111 &
#800
1*
1"
0+
0#
b101 $
b101 '
b0 %
b0 (
b1010000 &
#810
1*
1"
b1 %
b1 (
b1010001 &
#820
1*
1"
b10 %
b10 (
b1010010 &
#830
1*
1"
b11 %
b11 (
b1010011 &
#840
1*
1"
b100 %
b100 (
b1010100 &
#850
1)
1!
0*
0"
b101 %
b101 (
b1010101 &
#860
1+
1#
0)
0!
b110 %
b110 (
b1010110 &
#870
1+
1#
b111 %
b111 (
b1010111 &
#880
1+
1#
b1000 %
b1000 (
b1011000 &
#890
1+
1#
b1001 %
b1001 (
b1011001 &
#900
1+
1#
b1010 %
b1010 (
b1011010 &
#910
1+
1#
b1011 %
b1011 (
b1011011 &
#920
1+
1#
b1100 %
b1100 (
b1011100 &
#930
1+
1#
b1101 %
b1101 (
b1011101 &
#940
1+
1#
b1110 %
b1110 (
b1011110 &
#950
1+
1#
b1111 %
b1111 (
b1011111 &
#960
1*
1"
0+
0#
b110 $
b110 '
b0 %
b0 (
b1100000 &
#970
1*
1"
b1 %
b1 (
b1100001 &
#980
1*
1"
b10 %
b10 (
b1100010 &
#990
1*
1"
b11 %
b11 (
b1100011 &
#1000
1*
1"
b100 %
b100 (
b1100100 &
#1010
1*
1"
b101 %
b101 (
b1100101 &
#1020
1)
1!
0*
0"
b110 %
b110 (
b1100110 &
#1030
1+
1#
0)
0!
b111 %
b111 (
b1100111 &
#1040
1+
1#
b1000 %
b1000 (
b1101000 &
#1050
1+
1#
b1001 %
b1001 (
b1101001 &
#1060
1+
1#
b1010 %
b1010 (
b1101010 &
#1070
1+
1#
b1011 %
b1011 (
b1101011 &
#1080
1+
1#
b1100 %
b1100 (
b1101100 &
#1090
1+
1#
b1101 %
b1101 (
b1101101 &
#1100
1+
1#
b1110 %
b1110 (
b1101110 &
#1110
1+
1#
b1111 %
b1111 (
b1101111 &
#1120
1*
1"
0+
0#
b111 $
b111 '
b0 %
b0 (
b1110000 &
#1130
1*
1"
b1 %
b1 (
b1110001 &
#1140
1*
1"
b10 %
b10 (
b1110010 &
#1150
1*
1"
b11 %
b11 (
b1110011 &
#1160
1*
1"
b100 %
b100 (
b1110100 &
#1170
1*
1"
b101 %
b101 (
b1110101 &
#1180
1*
1"
b110 %
b110 (
b1110110 &
#1190
1)
1!
0*
0"
b111 %
b111 (
b1110111 &
#1200
1+
1#
0)
0!
b1000 %
b1000 (
b1111000 &
#1210
1+
1#
b1001 %
b1001 (
b1111001 &
#1220
1+
1#
b1010 %
b1010 (
b1111010 &
#1230
1+
1#
b1011 %
b1011 (
b1111011 &
#1240
1+
1#
b1100 %
b1100 (
b1111100 &
#1250
1+
1#
b1101 %
b1101 (
b1111101 &
#1260
1+
1#
b1110 %
b1110 (
b1111110 &
#1270
1+
1#
b1111 %
b1111 (
b1111111 &
#1280
1*
1"
0+
0#
b1000 $
b1000 '
b0 %
b0 (
b10000000 &
#1290
1*
1"
b1 %
b1 (
b10000001 &
#1300
1*
1"
b10 %
b10 (
b10000010 &
#1310
1*
1"
b11 %
b11 (
b10000011 &
#1320
1*
1"
b100 %
b100 (
b10000100 &
#1330
1*
1"
b101 %
b101 (
b10000101 &
#1340
1*
1"
b110 %
b110 (
b10000110 &
#1350
1*
1"
b111 %
b111 (
b10000111 &
#1360
1)
1!
0*
0"
b1000 %
b1000 (
b10001000 &
#1370
1+
1#
0)
0!
b1001 %
b1001 (
b10001001 &
#1380
1+
1#
b1010 %
b1010 (
b10001010 &
#1390
1+
1#
b1011 %
b1011 (
b10001011 &
#1400
1+
1#
b1100 %
b1100 (
b10001100 &
#1410
1+
1#
b1101 %
b1101 (
b10001101 &
#1420
1+
1#
b1110 %
b1110 (
b10001110 &
#1430
1+
1#
b1111 %
b1111 (
b10001111 &
#1440
1*
1"
0+
0#
b1001 $
b1001 '
b0 %
b0 (
b10010000 &
#1450
1*
1"
b1 %
b1 (
b10010001 &
#1460
1*
1"
b10 %
b10 (
b10010010 &
#1470
1*
1"
b11 %
b11 (
b10010011 &
#1480
1*
1"
b100 %
b100 (
b10010100 &
#1490
1*
1"
b101 %
b101 (
b10010101 &
#1500
1*
1"
b110 %
b110 (
b10010110 &
#1510
1*
1"
b111 %
b111 (
b10010111 &
#1520
1*
1"
b1000 %
b1000 (
b10011000 &
#1530
1)
1!
0*
0"
b1001 %
b1001 (
b10011001 &
#1540
1+
1#
0)
0!
b1010 %
b1010 (
b10011010 &
#1550
1+
1#
b1011 %
b1011 (
b10011011 &
#1560
1+
1#
b1100 %
b1100 (
b10011100 &
#1570
1+
1#
b1101 %
b1101 (
b10011101 &
#1580
1+
1#
b1110 %
b1110 (
b10011110 &
#1590
1+
1#
b1111 %
b1111 (
b10011111 &
#1600
1*
1"
0+
0#
b1010 $
b1010 '
b0 %
b0 (
b10100000 &
#1610
1*
1"
b1 %
b1 (
b10100001 &
#1620
1*
1"
b10 %
b10 (
b10100010 &
#1630
1*
1"
b11 %
b11 (
b10100011 &
#1640
1*
1"
b100 %
b100 (
b10100100 &
#1650
1*
1"
b101 %
b101 (
b10100101 &
#1660
1*
1"
b110 %
b110 (
b10100110 &
#1670
1*
1"
b111 %
b111 (
b10100111 &
#1680
1*
1"
b1000 %
b1000 (
b10101000 &
#1690
1*
1"
b1001 %
b1001 (
b10101001 &
#1700
1)
1!
0*
0"
b1010 %
b1010 (
b10101010 &
#1710
1+
1#
0)
0!
b1011 %
b1011 (
b10101011 &
#1720
1+
1#
b1100 %
b1100 (
b10101100 &
#1730
1+
1#
b1101 %
b1101 (
b10101101 &
#1740
1+
1#
b1110 %
b1110 (
b10101110 &
#1750
1+
1#
b1111 %
b1111 (
b10101111 &
#1760
1*
1"
0+
0#
b1011 $
b1011 '
b0 %
b0 (
b10110000 &
#1770
1*
1"
b1 %
b1 (
b10110001 &
#1780
1*
1"
b10 %
b10 (
b10110010 &
#1790
1*
1"
b11 %
b11 (
b10110011 &
#1800
1*
1"
b100 %
b100 (
b10110100 &
#1810
1*
1"
b101 %
b101 (
b10110101 &
#1820
1*
1"
b110 %
b110 (
b10110110 &
#1830
1*
1"
b111 %
b111 (
b10110111 &
#1840
1*
1"
b1000 %
b1000 (
b10111000 &
#1850
1*
1"
b1001 %
b1001 (
b10111001 &
#1860
1*
1"
b1010 %
b1010 (
b10111010 &
#1870
1)
1!
0*
0"
b1011 %
b1011 (
b10111011 &
#1880
1+
1#
0)
0!
b1100 %
b1100 (
b10111100 &
#1890
1+
1#
b1101 %
b1101 (
b10111101 &
#1900
1+
1#
b1110 %
b1110 (
b10111110 &
#1910
1+
1#
b1111 %
b1111 (
b10111111 &
#1920
1*
1"
0+
0#
b1100 $
b1100 '
b0 %
b0 (
b11000000 &
#1930
1*
1"
b1 %
b1 (
b11000001 &
#1940
1*
1"
b10 %
b10 (
b11000010 &
#1950
1*
1"
b11 %
b11 (
b11000011 &
#1960
1*
1"
b100 %
b100 (
b11000100 &
#1970
1*
1"
b101 %
b101 (
b11000101 &
#1980
1*
1"
b110 %
b110 (
b11000110 &
#1990
1*
1"
b111 %
b111 (
b11000111 &
#2000
1*
1"
b1000 %
b1000 (
b11001000 &
#2010
1*
1"
b1001 %
b1001 (
b11001001 &
#2020
1*
1"
b1010 %
b1010 (
b11001010 &
#2030
1*
1"
b1011 %
b1011 (
b11001011 &
#2040
1)
1!
0*
0"
b1100 %
b1100 (
b11001100 &
#2050
1+
1#
0)
0!
b1101 %
b1101 (
b11001101 &
#2060
1+
1#
b1110 %
b1110 (
b11001110 &
#2070
1+
1#
b1111 %
b1111 (
b11001111 &
#2080
1*
1"
0+
0#
b1101 $
b1101 '
b0 %
b0 (
b11010000 &
#2090
1*
1"
b1 %
b1 (
b11010001 &
#2100
1*
1"
b10 %
b10 (
b11010010 &
#2110
1*
1"
b11 %
b11 (
b11010011 &
#2120
1*
1"
b100 %
b100 (
b11010100 &
#2130
1*
1"
b101 %
b101 (
b11010101 &
#2140
1*
1"
b110 %
b110 (
b11010110 &
#2150
1*
1"
b111 %
b111 (
b11010111 &
#2160
1*
1"
b1000 %
b1000 (
b11011000 &
#2170
1*
1"
b1001 %
b1001 (
b11011001 &
#2180
1*
1"
b1010 %
b1010 (
b11011010 &
#2190
1*
1"
b1011 %
b1011 (
b11011011 &
#2200
1*
1"
b1100 %
b1100 (
b11011100 &
#2210
1)
1!
0*
0"
b1101 %
b1101 (
b11011101 &
#2220
1+
1#
0)
0!
b1110 %
b1110 (
b11011110 &
#2230
1+
1#
b1111 %
b1111 (
b11011111 &
#2240
1*
1"
0+
0#
b1110 $
b1110 '
b0 %
b0 (
b11100000 &
#2250
1*
1"
b1 %
b1 (
b11100001 &
#2260
1*
1"
b10 %
b10 (
b11100010 &
#2270
1*
1"
b11 %
b11 (
b11100011 &
#2280
1*
1"
b100 %
b100 (
b11100100 &
#2290
1*
1"
b101 %
b101 (
b11100101 &
#2300
1*
1"
b110 %
b110 (
b11100110 &
#2310
1*
1"
b111 %
b111 (
b11100111 &
#2320
1*
1"
b1000 %
b1000 (
b11101000 &
#2330
1*
1"
b1001 %
b1001 (
b11101001 &
#2340
1*
1"
b1010 %
b1010 (
b11101010 &
#2350
1*
1"
b1011 %
b1011 (
b11101011 &
#2360
1*
1"
b1100 %
b1100 (
b11101100 &
#2370
1*
1"
b1101 %
b1101 (
b11101101 &
#2380
1)
1!
0*
0"
b1110 %
b1110 (
b11101110 &
#2390
1+
1#
0)
0!
b1111 %
b1111 (
b11101111 &
#2400
1*
1"
0+
0#
b1111 $
b1111 '
b0 %
b0 (
b11110000 &
#2410
1*
1"
b1 %
b1 (
b11110001 &
#2420
1*
1"
b10 %
b10 (
b11110010 &
#2430
1*
1"
b11 %
b11 (
b11110011 &
#2440
1*
1"
b100 %
b100 (
b11110100 &
#2450
1*
1"
b101 %
b101 (
b11110101 &
#2460
1*
1"
b110 %
b110 (
b11110110 &
#2470
1*
1"
b111 %
b111 (
b11110111 &
#2480
1*
1"
b1000 %
b1000 (
b11111000 &
#2490
1*
1"
b1001 %
b1001 (
b11111001 &
#2500
1*
1"
b1010 %
b1010 (
b11111010 &
#2510
1*
1"
b1011 %
b1011 (
b11111011 &
#2520
1*
1"
b1100 %
b1100 (
b11111100 &
#2530
1*
1"
b1101 %
b1101 (
b11111101 &
#2540
1*
1"
b1110 %
b1110 (
b11111110 &
#2550
1)
1!
0*
0"
b1111 %
b1111 (
b11111111 &
#2560
b100000000 &
