basic_projects/05_8to1_Mux/mux_8to1_gatelevel.v
module mux_8to1_gatelevel (input i0,i1,i2,i3,i4,i5,i6,i7,s0,s1,s2,E, output w0,w1,w2,w3,w4,w5,w6,w7,w8,Y);

wire s0_not,s1_not,s2_not;
not g0 (s0_not,s0);
not    g1 (s1_not,s1);
not    g2 (s2_not,s2);
and g3 (w0,s0_not,s1_not,s2_not,i0);
and    g4 (w1,s0_not,s1_not,s2,i1);
and    g5 (w2,s0_not,s1,s2_not,i2);
and    g6 (w3,s0_not,s1,s2,i3);
and    g7 (w4,s0,s1_not,s2_not,i4);
and    g8 (w5,s0,s1_not,s2,i5);
and    g9 (w6,s0,s1,s2_not,i6);
and    g10 (w7,s0,s1,s2,i7);
or  g11 (w8,w0,w1,w2,w3,w4,w5,w6,w7);
and g12 (Y,E,w8);
endmodule

05_8to1_Mux/mux_8to1_behavioural.v
module mux_8to1_behavioural (input i0,i1,i2,i3,i4,i5,i6,i7,s0,s1,s2,E, output reg Y);
    
always@(*)begin
if(E==0)
Y=0;
else begin 
case ({s2,s1,s0})
3'b000: Y = i0;
3'b001: Y = i1;
3'b010: Y = i2;
3'b011: Y = i3;
3'b100: Y = i4;
3'b101: Y = i5;
3'b110: Y = i6;
3'b111: Y = i7;
default: Y = 0;

endcase
end
end

endmodule

basic_projects/05_8to1_Mux/testbench.v
`timescale 1ns/1ps

module testbench;
reg i0,i1,i2,i3,i4,i5,i6,i7,s0,s1,s2,E;
wire w0_gate,w1_gate,w2_gate,w3_gate,w4_gate,w5_gate,w6_gate,w7_gate,w8_gate,Y_gate,Y_behav;

mux_8to1_behavioural behav(i0,i1,i2,i3,i4,i5,i6,i7,s0,s1,s2,E,Y_behav);
mux_8to1_gatelevel gate(i0,i1,i2,i3,i4,i5,i6,i7,s0,s1,s2,E,w0_gate,w1_gate,w2_gate,w3_gate,w4_gate,w5_gate,w6_gate,w7_gate,w8_gate,Y_gate);

integer i;

initial begin 
$dumpfile("mux_8to1.vcd");
$dumpvars(0,testbench);
//Case-1 when enable is 0;
E=0;
s0 = 1'bx;
s1 = 1'bx;
s2 = 1'bx;
i0 = 0; i1 = 0; i2 = 0; i3 = 0;
i4 = 0; i5 = 0; i6 = 0; i7 = 0;
#10
$display("When E=0 the Y_gate=%b and Y_behav=%b", Y_gate,Y_behav);
E=1;
for(i=0;i<2048;i=i+1)
begin 
{i0,i1,i2,i3,i4,i5,i6,i7,s0,s1,s2}=i[10:0];
#10
$display("i0=%b,i1=%b,i2=%b,i3=%b,i4=%b,i5=%b,i6=%b,i7=%b,s0=%b,s1=%b,s2=%b,E=%b,Y_gate=%b,Y_behav=%b",i0,i1,i2,i3,i4,i5,i6,i7,s0,s1,s2,E,Y_gate,Y_gate);
end
$finish;
end






endmodule

basic_projects/05_8to1_Mux/mux_8to1.vcd
$date
	Mon Jun 16 18:56:13 2025
$end
$version
	Icarus Verilog
$end
$timescale
	1ps
$end
$scope module testbench $end
$var wire 1 ! Y_behav $end
$var wire 1 " Y_gate $end
$var wire 1 # w0_gate $end
$var wire 1 $ w1_gate $end
$var wire 1 % w2_gate $end
$var wire 1 & w3_gate $end
$var wire 1 ' w4_gate $end
$var wire 1 ( w5_gate $end
$var wire 1 ) w6_gate $end
$var wire 1 * w7_gate $end
$var wire 1 + w8_gate $end
$var reg 1 , E $end
$var integer 32 - i [31:0] $end
$var reg 1 . i0 $end
$var reg 1 / i1 $end
$var reg 1 0 i2 $end
$var reg 1 1 i3 $end
$var reg 1 2 i4 $end
$var reg 1 3 i5 $end
$var reg 1 4 i6 $end
$var reg 1 5 i7 $end
$var reg 1 6 s0 $end
$var reg 1 7 s1 $end
$var reg 1 8 s2 $end
$scope module behav $end
$var wire 1 9 E $end
$var wire 1 : i0 $end
$var wire 1 ; i1 $end
$var wire 1 < i2 $end
$var wire 1 = i3 $end
$var wire 1 > i4 $end
$var wire 1 ? i5 $end
$var wire 1 @ i6 $end
$var wire 1 A i7 $end
$var wire 1 B s0 $end
$var wire 1 C s1 $end
$var wire 1 D s2 $end
$var reg 1 E Y $end
$upscope $end
$scope module gate $end
$var wire 1 9 E $end
$var wire 1 " Y $end
$var wire 1 : i0 $end
$var wire 1 ; i1 $end
$var wire 1 < i2 $end
$var wire 1 = i3 $end
$var wire 1 > i4 $end
$var wire 1 ? i5 $end
$var wire 1 @ i6 $end
$var wire 1 A i7 $end
$var wire 1 B s0 $end
$var wire 1 F s0_not $end
$var wire 1 C s1 $end
$var wire 1 G s1_not $end
$var wire 1 D s2 $end
$var wire 1 H s2_not $end
$var wire 1 # w0 $end
$var wire 1 $ w1 $end
$var wire 1 % w2 $end
$var wire 1 & w3 $end
$var wire 1 ' w4 $end
$var wire 1 ( w5 $end
$var wire 1 ) w6 $end
$var wire 1 * w7 $end
$var wire 1 + w8 $end
$upscope $end
$upscope $end
$enddefinitions $end
#0
$dumpvars
xH
xG
xF
0E
xD
xC
xB
0A
0@
0?
0>
0=
0<
0;
0:
09
x8
x7
x6
05
04
03
02
01
00
0/
0.
bx -
0,
0+
0*
0)
0(
0'
0&
0%
0$
0#
0"
0!
$end
#10000
1F
1G
1H
06
0B
07
0C
08
0D
b0 -
1,
19
#20000
0H
18
1D
b1 -
#30000
0G
1H
17
1C
08
0D
b10 -
#40000
0H
18
1D
b11 -
#50000
0F
1G
1H
16
1B
07
0C
08
0D
b100 -
#60000
0H
18
1D
b101 -
#70000
0G
1H
17
1C
08
0D
b110 -
#80000
0H
18
1D
b111 -
#90000
1F
1G
1H
15
1A
06
0B
07
0C
08
0D
b1000 -
#100000
0H
18
1D
b1001 -
#110000
0G
1H
17
1C
08
0D
b1010 -
#120000
0H
18
1D
b1011 -
#130000
0F
1G
1H
16
1B
07
0C
08
0D
b1100 -
#140000
0H
18
1D
b1101 -
#150000
0G
1H
17
1C
08
0D
b1110 -
#160000
1"
1+
1E
1!
0H
1*
18
1D
b1111 -
#170000
0"
0+
1F
1G
0E
0!
1H
0*
14
1@
05
0A
06
0B
07
0C
08
0D
b10000 -
#180000
0H
18
1D
b10001 -
#190000
0G
1H
17
1C
08
0D
b10010 -
#200000
1E
1!
0H
18
1D
b10011 -
#210000
0F
1G
0E
0!
1H
16
1B
07
0C
08
0D
b10100 -
#220000
0H
18
1D
b10101 -
#230000
1"
1+
0G
1)
1H
17
1C
08
0D
b10110 -
#240000
0"
0+
0)
0H
18
1D
b10111 -
#250000
1F
1G
1H
15
1A
06
0B
07
0C
08
0D
b11000 -
#260000
0H
18
1D
b11001 -
#270000
0G
1H
17
1C
08
0D
b11010 -
#280000
1E
1!
0H
18
1D
b11011 -
#290000
0F
1G
0E
0!
1H
16
1B
07
0C
08
0D
b11100 -
#300000
0H
18
1D
b11101 -
#310000
1"
1+
0G
1)
1H
17
1C
08
0D
b11110 -
#320000
0)
1E
1!
0H
1*
18
1D
b11111 -
#330000
0"
0+
1F
1G
0E
0!
1H
0*
13
1?
04
0@
05
0A
06
0B
07
0C
08
0D
b100000 -
#340000
0H
18
1D
b100001 -
#350000
0G
1H
17
1C
08
0D
b100010 -
#360000
0H
18
1D
b100011 -
#370000
0F
1G
1H
16
1B
07
0C
08
0D
b100100 -
#380000
1"
1+
1E
1!
0H
1(
18
1D
b100101 -
#390000
0"
0+
0G
0E
0!
1H
0(
17
1C
08
0D
b100110 -
#400000
0H
18
1D
b100111 -
#410000
1F
1G
1H
15
1A
06
0B
07
0C
08
0D
b101000 -
#420000
0H
18
1D
b101001 -
#430000
0G
1H
17
1C
08
0D
b101010 -
#440000
0H
18
1D
b101011 -
#450000
0F
1G
1H
16
1B
07
0C
08
0D
b101100 -
#460000
1"
1+
1E
1!
0H
1(
18
1D
b101101 -
#470000
0"
0+
0G
0E
0!
1H
0(
17
1C
08
0D
b101110 -
#480000
1"
1+
1E
1!
0H
1*
18
1D
b101111 -
#490000
0"
0+
1F
1G
0E
0!
1H
0*
14
1@
05
0A
06
0B
07
0C
08
0D
b110000 -
#500000
0H
18
1D
b110001 -
#510000
0G
1H
17
1C
08
0D
b110010 -
#520000
1E
1!
0H
18
1D
b110011 -
#530000
0F
1G
0E
0!
1H
16
1B
07
0C
08
0D
b110100 -
#540000
1"
1+
1E
1!
0H
1(
18
1D
b110101 -
#550000
0G
1)
0E
0!
1H
0(
17
1C
08
0D
b110110 -
#560000
0"
0+
0)
0H
18
1D
b110111 -
#570000
1F
1G
1H
15
1A
06
0B
07
0C
08
0D
b111000 -
#580000
0H
18
1D
b111001 -
#590000
0G
1H
17
1C
08
0D
b111010 -
#600000
1E
1!
0H
18
1D
b111011 -
#610000
0F
1G
0E
0!
1H
16
1B
07
0C
08
0D
b111100 -
#620000
1"
1+
1E
1!
0H
1(
18
1D
b111101 -
#630000
0G
1)
0E
0!
1H
0(
17
1C
08
0D
b111110 -
#640000
0)
1E
1!
0H
1*
18
1D
b111111 -
#650000
0"
0+
1F
1G
0E
0!
1H
0*
12
1>
03
0?
04
0@
05
0A
06
0B
07
0C
08
0D
b1000000 -
#660000
1E
1!
0H
18
1D
b1000001 -
#670000
0G
0E
0!
1H
17
1C
08
0D
b1000010 -
#680000
0H
18
1D
b1000011 -
#690000
1"
1+
0F
1'
1G
1H
16
1B
07
0C
08
0D
b1000100 -
#700000
0"
0+
0'
0H
18
1D
b1000101 -
#710000
0G
1H
17
1C
08
0D
b1000110 -
#720000
0H
18
1D
b1000111 -
#730000
1F
1G
1H
15
1A
06
0B
07
0C
08
0D
b1001000 -
#740000
1E
1!
0H
18
1D
b1001001 -
#750000
0G
0E
0!
1H
17
1C
08
0D
b1001010 -
#760000
0H
18
1D
b1001011 -
#770000
1"
1+
0F
1'
1G
1H
16
1B
07
0C
08
0D
b1001100 -
#780000
0"
0+
0'
0H
18
1D
b1001101 -
#790000
0G
1H
17
1C
08
0D
b1001110 -
#800000
1"
1+
1E
1!
0H
1*
18
1D
b1001111 -
#810000
0"
0+
1F
1G
0E
0!
1H
0*
14
1@
05
0A
06
0B
07
0C
08
0D
b1010000 -
#820000
1E
1!
0H
18
1D
b1010001 -
#830000
0G
0E
0!
1H
17
1C
08
0D
b1010010 -
#840000
1E
1!
0H
18
1D
b1010011 -
#850000
1"
1+
0F
1'
1G
0E
0!
1H
16
1B
07
0C
08
0D
b1010100 -
#860000
0"
0+
0'
0H
18
1D
b1010101 -
#870000
1"
1+
0G
1)
1H
17
1C
08
0D
b1010110 -
#880000
0"
0+
0)
0H
18
1D
b1010111 -
#890000
1F
1G
1H
15
1A
06
0B
07
0C
08
0D
b1011000 -
#900000
1E
1!
0H
18
1D
b1011001 -
#910000
0G
0E
0!
1H
17
1C
08
0D
b1011010 -
#920000
1E
1!
0H
18
1D
b1011011 -
#930000
1"
1+
0F
1'
1G
0E
0!
1H
16
1B
07
0C
08
0D
b1011100 -
#940000
0"
0+
0'
0H
18
1D
b1011101 -
#950000
1"
1+
0G
1)
1H
17
1C
08
0D
b1011110 -
#960000
0)
1E
1!
0H
1*
18
1D
b1011111 -
#970000
0"
0+
1F
1G
0E
0!
1H
0*
13
1?
04
0@
05
0A
06
0B
07
0C
08
0D
b1100000 -
#980000
1E
1!
0H
18
1D
b1100001 -
#990000
0G
0E
0!
1H
17
1C
08
0D
b1100010 -
#1000000
0H
18
1D
b1100011 -
#1010000
1"
1+
0F
1'
1G
1H
16
1B
07
0C
08
0D
b1100100 -
#1020000
0'
1E
1!
0H
1(
18
1D
b1100101 -
#1030000
0"
0+
0G
0E
0!
1H
0(
17
1C
08
0D
b1100110 -
#1040000
0H
18
1D
b1100111 -
#1050000
1F
1G
1H
15
1A
06
0B
07
0C
08
0D
b1101000 -
#1060000
1E
1!
0H
18
1D
b1101001 -
#1070000
0G
0E
0!
1H
17
1C
08
0D
b1101010 -
#1080000
0H
18
1D
b1101011 -
#1090000
1"
1+
0F
1'
1G
1H
16
1B
07
0C
08
0D
b1101100 -
#1100000
0'
1E
1!
0H
1(
18
1D
b1101101 -
#1110000
0"
0+
0G
0E
0!
1H
0(
17
1C
08
0D
b1101110 -
#1120000
1"
1+
1E
1!
0H
1*
18
1D
b1101111 -
#1130000
0"
0+
1F
1G
0E
0!
1H
0*
14
1@
05
0A
06
0B
07
0C
08
0D
b1110000 -
#1140000
1E
1!
0H
18
1D
b1110001 -
#1150000
0G
0E
0!
1H
17
1C
08
0D
b1110010 -
#1160000
1E
1!
0H
18
1D
b1110011 -
#1170000
1"
1+
0F
1'
1G
0E
0!
1H
16
1B
07
0C
08
0D
b1110100 -
#1180000
0'
1E
1!
0H
1(
18
1D
b1110101 -
#1190000
0G
1)
0E
0!
1H
0(
17
1C
08
0D
b1110110 -
#1200000
0"
0+
0)
0H
18
1D
b1110111 -
#1210000
1F
1G
1H
15
1A
06
0B
07
0C
08
0D
b1111000 -
#1220000
1E
1!
0H
18
1D
b1111001 -
#1230000
0G
0E
0!
1H
17
1C
08
0D
b1111010 -
#1240000
1E
1!
0H
18
1D
b1111011 -
#1250000
1"
1+
0F
1'
1G
0E
0!
1H
16
1B
07
0C
08
0D
b1111100 -
#1260000
0'
1E
1!
0H
1(
18
1D
b1111101 -
#1270000
0G
1)
0E
0!
1H
0(
17
1C
08
0D
b1111110 -
#1280000
0)
1E
1!
0H
1*
18
1D
b1111111 -
#1290000
0"
0+
1F
1G
0E
0!
1H
0*
11
1=
02
0>
03
0?
04
0@
05
0A
06
0B
07
0C
08
0D
b10000000 -
#1300000
0H
18
1D
b10000001 -
#1310000
0G
1H
17
1C
08
0D
b10000010 -
#1320000
1"
1+
0H
1&
18
1D
b10000011 -
#1330000
0"
0+
0F
1G
1H
0&
16
1B
07
0C
08
0D
b10000100 -
#1340000
0H
18
1D
b10000101 -
#1350000
0G
1E
1!
1H
17
1C
08
0D
b10000110 -
#1360000
0E
0!
0H
18
1D
b10000111 -
#1370000
1F
1G
1H
15
1A
06
0B
07
0C
08
0D
b10001000 -
#1380000
0H
18
1D
b10001001 -
#1390000
0G
1H
17
1C
08
0D
b10001010 -
#1400000
1"
1+
0H
1&
18
1D
b10001011 -
#1410000
0"
0+
0F
1G
1H
0&
16
1B
07
0C
08
0D
b10001100 -
#1420000
0H
18
1D
b10001101 -
#1430000
0G
1E
1!
1H
17
1C
08
0D
b10001110 -
#1440000
1"
1+
0H
1*
18
1D
b10001111 -
#1450000
0"
0+
1F
1G
0E
0!
1H
0*
14
1@
05
0A
06
0B
07
0C
08
0D
b10010000 -
#1460000
0H
18
1D
b10010001 -
#1470000
0G
1H
17
1C
08
0D
b10010010 -
#1480000
1"
1+
1E
1!
0H
1&
18
1D
b10010011 -
#1490000
0"
0+
0F
1G
0E
0!
1H
0&
16
1B
07
0C
08
0D
b10010100 -
#1500000
0H
18
1D
b10010101 -
#1510000
1"
1+
0G
1)
1E
1!
1H
17
1C
08
0D
b10010110 -
#1520000
0"
0+
0)
0E
0!
0H
18
1D
b10010111 -
#1530000
1F
1G
1H
15
1A
06
0B
07
0C
08
0D
b10011000 -
#1540000
0H
18
1D
b10011001 -
#1550000
0G
1H
17
1C
08
0D
b10011010 -
#1560000
1"
1+
1E
1!
0H
1&
18
1D
b10011011 -
#1570000
0"
0+
0F
1G
0E
0!
1H
0&
16
1B
07
0C
08
0D
b10011100 -
#1580000
0H
18
1D
b10011101 -
#1590000
1"
1+
0G
1)
1E
1!
1H
17
1C
08
0D
b10011110 -
#1600000
0)
0H
1*
18
1D
b10011111 -
#1610000
0"
0+
1F
1G
0E
0!
1H
0*
13
1?
04
0@
05
0A
06
0B
07
0C
08
0D
b10100000 -
#1620000
0H
18
1D
b10100001 -
#1630000
0G
1H
17
1C
08
0D
b10100010 -
#1640000
1"
1+
0H
1&
18
1D
b10100011 -
#1650000
0"
0+
0F
1G
1H
0&
16
1B
07
0C
08
0D
b10100100 -
#1660000
1"
1+
1E
1!
0H
1(
18
1D
b10100101 -
#1670000
0"
0+
0G
1H
0(
17
1C
08
0D
b10100110 -
#1680000
0E
0!
0H
18
1D
b10100111 -
#1690000
1F
1G
1H
15
1A
06
0B
07
0C
08
0D
b10101000 -
#1700000
0H
18
1D
b10101001 -
#1710000
0G
1H
17
1C
08
0D
b10101010 -
#1720000
1"
1+
0H
1&
18
1D
b10101011 -
#1730000
0"
0+
0F
1G
1H
0&
16
1B
07
0C
08
0D
b10101100 -
#1740000
1"
1+
1E
1!
0H
1(
18
1D
b10101101 -
#1750000
0"
0+
0G
1H
0(
17
1C
08
0D
b10101110 -
#1760000
1"
1+
0H
1*
18
1D
b10101111 -
#1770000
0"
0+
1F
1G
0E
0!
1H
0*
14
1@
05
0A
06
0B
07
0C
08
0D
b10110000 -
#1780000
0H
18
1D
b10110001 -
#1790000
0G
1H
17
1C
08
0D
b10110010 -
#1800000
1"
1+
1E
1!
0H
1&
18
1D
b10110011 -
#1810000
0"
0+
0F
1G
0E
0!
1H
0&
16
1B
07
0C
08
0D
b10110100 -
#1820000
1"
1+
1E
1!
0H
1(
18
1D
b10110101 -
#1830000
0G
1)
1H
0(
17
1C
08
0D
b10110110 -
#1840000
0"
0+
0)
0E
0!
0H
18
1D
b10110111 -
#1850000
1F
1G
1H
15
1A
06
0B
07
0C
08
0D
b10111000 -
#1860000
0H
18
1D
b10111001 -
#1870000
0G
1H
17
1C
08
0D
b10111010 -
#1880000
1"
1+
1E
1!
0H
1&
18
1D
b10111011 -
#1890000
0"
0+
0F
1G
0E
0!
1H
0&
16
1B
07
0C
08
0D
b10111100 -
#1900000
1"
1+
1E
1!
0H
1(
18
1D
b10111101 -
#1910000
0G
1)
1H
0(
17
1C
08
0D
b10111110 -
#1920000
0)
0H
1*
18
1D
b10111111 -
#1930000
0"
0+
1F
1G
0E
0!
1H
0*
12
1>
03
0?
04
0@
05
0A
06
0B
07
0C
08
0D
b11000000 -
#1940000
1E
1!
0H
18
1D
b11000001 -
#1950000
0G
0E
0!
1H
17
1C
08
0D
b11000010 -
#1960000
1"
1+
0H
1&
18
1D
b11000011 -
#1970000
0F
1'
1G
1H
0&
16
1B
07
0C
08
0D
b11000100 -
#1980000
0"
0+
0'
0H
18
1D
b11000101 -
#1990000
0G
1E
1!
1H
17
1C
08
0D
b11000110 -
#2000000
0E
0!
0H
18
1D
b11000111 -
#2010000
1F
1G
1H
15
1A
06
0B
07
0C
08
0D
b11001000 -
#2020000
1E
1!
0H
18
1D
b11001001 -
#2030000
0G
0E
0!
1H
17
1C
08
0D
b11001010 -
#2040000
1"
1+
0H
1&
18
1D
b11001011 -
#2050000
0F
1'
1G
1H
0&
16
1B
07
0C
08
0D
b11001100 -
#2060000
0"
0+
0'
0H
18
1D
b11001101 -
#2070000
0G
1E
1!
1H
17
1C
08
0D
b11001110 -
#2080000
1"
1+
0H
1*
18
1D
b11001111 -
#2090000
0"
0+
1F
1G
0E
0!
1H
0*
14
1@
05
0A
06
0B
07
0C
08
0D
b11010000 -
#2100000
1E
1!
0H
18
1D
b11010001 -
#2110000
0G
0E
0!
1H
17
1C
08
0D
b11010010 -
#2120000
1"
1+
1E
1!
0H
1&
18
1D
b11010011 -
#2130000
0F
1'
1G
0E
0!
1H
0&
16
1B
07
0C
08
0D
b11010100 -
#2140000
0"
0+
0'
0H
18
1D
b11010101 -
#2150000
1"
1+
0G
1)
1E
1!
1H
17
1C
08
0D
b11010110 -
#2160000
0"
0+
0)
0E
0!
0H
18
1D
b11010111 -
#2170000
1F
1G
1H
15
1A
06
0B
07
0C
08
0D
b11011000 -
#2180000
1E
1!
0H
18
1D
b11011001 -
#2190000
0G
0E
0!
1H
17
1C
08
0D
b11011010 -
#2200000
1"
1+
1E
1!
0H
1&
18
1D
b11011011 -
#2210000
0F
1'
1G
0E
0!
1H
0&
16
1B
07
0C
08
0D
b11011100 -
#2220000
0"
0+
0'
0H
18
1D
b11011101 -
#2230000
1"
1+
0G
1)
1E
1!
1H
17
1C
08
0D
b11011110 -
#2240000
0)
0H
1*
18
1D
b11011111 -
#2250000
0"
0+
1F
1G
0E
0!
1H
0*
13
1?
04
0@
05
0A
06
0B
07
0C
08
0D
b11100000 -
#2260000
1E
1!
0H
18
1D
b11100001 -
#2270000
0G
0E
0!
1H
17
1C
08
0D
b11100010 -
#2280000
1"
1+
0H
1&
18
1D
b11100011 -
#2290000
0F
1'
1G
1H
0&
16
1B
07
0C
08
0D
b11100100 -
#2300000
0'
1E
1!
0H
1(
18
1D
b11100101 -
#2310000
0"
0+
0G
1H
0(
17
1C
08
0D
b11100110 -
#2320000
0E
0!
0H
18
1D
b11100111 -
#2330000
1F
1G
1H
15
1A
06
0B
07
0C
08
0D
b11101000 -
#2340000
1E
1!
0H
18
1D
b11101001 -
#2350000
0G
0E
0!
1H
17
1C
08
0D
b11101010 -
#2360000
1"
1+
0H
1&
18
1D
b11101011 -
#2370000
0F
1'
1G
1H
0&
16
1B
07
0C
08
0D
b11101100 -
#2380000
0'
1E
1!
0H
1(
18
1D
b11101101 -
#2390000
0"
0+
0G
1H
0(
17
1C
08
0D
b11101110 -
#2400000
1"
1+
0H
1*
18
1D
b11101111 -
#2410000
0"
0+
1F
1G
0E
0!
1H
0*
14
1@
05
0A
06
0B
07
0C
08
0D
b11110000 -
#2420000
1E
1!
0H
18
1D
b11110001 -
#2430000
0G
0E
0!
1H
17
1C
08
0D
b11110010 -
#2440000
1"
1+
1E
1!
0H
1&
18
1D
b11110011 -
#2450000
0F
1'
1G
0E
0!
1H
0&
16
1B
07
0C
08
0D
b11110100 -
#2460000
0'
1E
1!
0H
1(
18
1D
b11110101 -
#2470000
0G
1)
1H
0(
17
1C
08
0D
b11110110 -
#2480000
0"
0+
0)
0E
0!
0H
18
1D
b11110111 -
#2490000
1F
1G
1H
15
1A
06
0B
07
0C
08
0D
b11111000 -
#2500000
1E
1!
0H
18
1D
b11111001 -
#2510000
0G
0E
0!
1H
17
1C
08
0D
b11111010 -
#2520000
1"
1+
1E
1!
0H
1&
18
1D
b11111011 -
#2530000
0F
1'
1G
0E
0!
1H
0&
16
1B
07
0C
08
0D
b11111100 -
#2540000
0'
1E
1!
0H
1(
18
1D
b11111101 -
#2550000
0G
1)
1H
0(
17
1C
08
0D
b11111110 -
#2560000
0)
0H
1*
18
1D
b11111111 -
#2570000
0"
0+
1F
1G
0E
0!
1H
0*
10
1<
01
0=
02
0>
03
0?
04
0@
05
0A
06
0B
07
0C
08
0D
b100000000 -
#2580000
0H
18
1D
b100000001 -
#2590000
1"
1+
0G
1%
1E
1!
1H
17
1C
08
0D
b100000010 -
#2600000
0"
0+
0%
0E
0!
0H
18
1D
b100000011 -
#2610000
0F
1G
1H
16
1B
07
0C
08
0D
b100000100 -
#2620000
0H
18
1D
b100000101 -
#2630000
0G
1H
17
1C
08
0D
b100000110 -
#2640000
0H
18
1D
b100000111 -
#2650000
1F
1G
1H
15
1A
06
0B
07
0C
08
0D
b100001000 -
#2660000
0H
18
1D
b100001001 -
#2670000
1"
1+
0G
1%
1E
1!
1H
17
1C
08
0D
b100001010 -
#2680000
0"
0+
0%
0E
0!
0H
18
1D
b100001011 -
#2690000
0F
1G
1H
16
1B
07
0C
08
0D
b100001100 -
#2700000
0H
18
1D
b100001101 -
#2710000
0G
1H
17
1C
08
0D
b100001110 -
#2720000
1"
1+
1E
1!
0H
1*
18
1D
b100001111 -
#2730000
0"
0+
1F
1G
0E
0!
1H
0*
14
1@
05
0A
06
0B
07
0C
08
0D
b100010000 -
#2740000
0H
18
1D
b100010001 -
#2750000
1"
1+
0G
1%
1E
1!
1H
17
1C
08
0D
b100010010 -
#2760000
0"
0+
0%
0H
18
1D
b100010011 -
#2770000
0F
1G
0E
0!
1H
16
1B
07
0C
08
0D
b100010100 -
#2780000
0H
18
1D
b100010101 -
#2790000
1"
1+
0G
1)
1H
17
1C
08
0D
b100010110 -
#2800000
0"
0+
0)
0H
18
1D
b100010111 -
#2810000
1F
1G
1H
15
1A
06
0B
07
0C
08
0D
b100011000 -
#2820000
0H
18
1D
b100011001 -
#2830000
1"
1+
0G
1%
1E
1!
1H
17
1C
08
0D
b100011010 -
#2840000
0"
0+
0%
0H
18
1D
b100011011 -
#2850000
0F
1G
0E
0!
1H
16
1B
07
0C
08
0D
b100011100 -
#2860000
0H
18
1D
b100011101 -
#2870000
1"
1+
0G
1)
1H
17
1C
08
0D
b100011110 -
#2880000
0)
1E
1!
0H
1*
18
1D
b100011111 -
#2890000
0"
0+
1F
1G
0E
0!
1H
0*
13
1?
04
0@
05
0A
06
0B
07
0C
08
0D
b100100000 -
#2900000
0H
18
1D
b100100001 -
#2910000
1"
1+
0G
1%
1E
1!
1H
17
1C
08
0D
b100100010 -
#2920000
0"
0+
0%
0E
0!
0H
18
1D
b100100011 -
#2930000
0F
1G
1H
16
1B
07
0C
08
0D
b100100100 -
#2940000
1"
1+
1E
1!
0H
1(
18
1D
b100100101 -
#2950000
0"
0+
0G
0E
0!
1H
0(
17
1C
08
0D
b100100110 -
#2960000
0H
18
1D
b100100111 -
#2970000
1F
1G
1H
15
1A
06
0B
07
0C
08
0D
b100101000 -
#2980000
0H
18
1D
b100101001 -
#2990000
1"
1+
0G
1%
1E
1!
1H
17
1C
08
0D
b100101010 -
#3000000
0"
0+
0%
0E
0!
0H
18
1D
b100101011 -
#3010000
0F
1G
1H
16
1B
07
0C
08
0D
b100101100 -
#3020000
1"
1+
1E
1!
0H
1(
18
1D
b100101101 -
#3030000
0"
0+
0G
0E
0!
1H
0(
17
1C
08
0D
b100101110 -
#3040000
1"
1+
1E
1!
0H
1*
18
1D
b100101111 -
#3050000
0"
0+
1F
1G
0E
0!
1H
0*
14
1@
05
0A
06
0B
07
0C
08
0D
b100110000 -
#3060000
0H
18
1D
b100110001 -
#3070000
1"
1+
0G
1%
1E
1!
1H
17
1C
08
0D
b100110010 -
#3080000
0"
0+
0%
0H
18
1D
b100110011 -
#3090000
0F
1G
0E
0!
1H
16
1B
07
0C
08
0D
b100110100 -
#3100000
1"
1+
1E
1!
0H
1(
18
1D
b100110101 -
#3110000
0G
1)
0E
0!
1H
0(
17
1C
08
0D
b100110110 -
#3120000
0"
0+
0)
0H
18
1D
b100110111 -
#3130000
1F
1G
1H
15
1A
06
0B
07
0C
08
0D
b100111000 -
#3140000
0H
18
1D
b100111001 -
#3150000
1"
1+
0G
1%
1E
1!
1H
17
1C
08
0D
b100111010 -
#3160000
0"
0+
0%
0H
18
1D
b100111011 -
#3170000
0F
1G
0E
0!
1H
16
1B
07
0C
08
0D
b100111100 -
#3180000
1"
1+
1E
1!
0H
1(
18
1D
b100111101 -
#3190000
0G
1)
0E
0!
1H
0(
17
1C
08
0D
b100111110 -
#3200000
0)
1E
1!
0H
1*
18
1D
b100111111 -
#3210000
0"
0+
1F
1G
0E
0!
1H
0*
12
1>
03
0?
04
0@
05
0A
06
0B
07
0C
08
0D
b101000000 -
#3220000
1E
1!
0H
18
1D
b101000001 -
#3230000
1"
1+
0G
1%
1H
17
1C
08
0D
b101000010 -
#3240000
0"
0+
0%
0E
0!
0H
18
1D
b101000011 -
#3250000
1"
1+
0F
1'
1G
1H
16
1B
07
0C
08
0D
b101000100 -
#3260000
0"
0+
0'
0H
18
1D
b101000101 -
#3270000
0G
1H
17
1C
08
0D
b101000110 -
#3280000
0H
18
1D
b101000111 -
#3290000
1F
1G
1H
15
1A
06
0B
07
0C
08
0D
b101001000 -
#3300000
1E
1!
0H
18
1D
b101001001 -
#3310000
1"
1+
0G
1%
1H
17
1C
08
0D
b101001010 -
#3320000
0"
0+
0%
0E
0!
0H
18
1D
b101001011 -
#3330000
1"
1+
0F
1'
1G
1H
16
1B
07
0C
08
0D
b101001100 -
#3340000
0"
0+
0'
0H
18
1D
b101001101 -
#3350000
0G
1H
17
1C
08
0D
b101001110 -
#3360000
1"
1+
1E
1!
0H
1*
18
1D
b101001111 -
#3370000
0"
0+
1F
1G
0E
0!
1H
0*
14
1@
05
0A
06
0B
07
0C
08
0D
b101010000 -
#3380000
1E
1!
0H
18
1D
b101010001 -
#3390000
1"
1+
0G
1%
1H
17
1C
08
0D
b101010010 -
#3400000
0"
0+
0%
0H
18
1D
b101010011 -
#3410000
1"
1+
0F
1'
1G
0E
0!
1H
16
1B
07
0C
08
0D
b101010100 -
#3420000
0"
0+
0'
0H
18
1D
b101010101 -
#3430000
1"
1+
0G
1)
1H
17
1C
08
0D
b101010110 -
#3440000
0"
0+
0)
0H
18
1D
b101010111 -
#3450000
1F
1G
1H
15
1A
06
0B
07
0C
08
0D
b101011000 -
#3460000
1E
1!
0H
18
1D
b101011001 -
#3470000
1"
1+
0G
1%
1H
17
1C
08
0D
b101011010 -
#3480000
0"
0+
0%
0H
18
1D
b101011011 -
#3490000
1"
1+
0F
1'
1G
0E
0!
1H
16
1B
07
0C
08
0D
b101011100 -
#3500000
0"
0+
0'
0H
18
1D
b101011101 -
#3510000
1"
1+
0G
1)
1H
17
1C
08
0D
b101011110 -
#3520000
0)
1E
1!
0H
1*
18
1D
b101011111 -
#3530000
0"
0+
1F
1G
0E
0!
1H
0*
13
1?
04
0@
05
0A
06
0B
07
0C
08
0D
b101100000 -
#3540000
1E
1!
0H
18
1D
b101100001 -
#3550000
1"
1+
0G
1%
1H
17
1C
08
0D
b101100010 -
#3560000
0"
0+
0%
0E
0!
0H
18
1D
b101100011 -
#3570000
1"
1+
0F
1'
1G
1H
16
1B
07
0C
08
0D
b101100100 -
#3580000
0'
1E
1!
0H
1(
18
1D
b101100101 -
#3590000
0"
0+
0G
0E
0!
1H
0(
17
1C
08
0D
b101100110 -
#3600000
0H
18
1D
b101100111 -
#3610000
1F
1G
1H
15
1A
06
0B
07
0C
08
0D
b101101000 -
#3620000
1E
1!
0H
18
1D
b101101001 -
#3630000
1"
1+
0G
1%
1H
17
1C
08
0D
b101101010 -
