Intermediate_Projects/03_ALU_4_Bit/ALU_4_Bit.v
`timescale 1ns/1ns

module ALU_4_Bit(input [3:0]a,input [3:0]b, input [2:0] sel,output reg  [3:0] result,output reg  carry,output reg  zero);
reg [4:0] temp;
always @(*) begin
    case(sel)
    3'b000: begin temp=a+b;
    result=temp[3:0];
    carry=temp[4]; 
    end
    3'b001: begin result=a-b; 
    temp = a-b;
    result = temp[3:0];
    carry= (a<b);
    end
    3'b010: begin result=a&b; end
    3'b011: begin result=a|b; end
    3'b100: begin result=a^b; end
    3'b101: begin result=~a;end
    3'b110: begin result=a<<1;end
    3'b111: begin result=a>>1; end

    endcase
    zero=(result==4'b0000);
end


endmodule

Intermediate_Projects/03_ALU_4_Bit/testbench.v
module testbench;
reg [3:0]a;
reg [3:0]b; 
reg [2:0] sel;
wire [3:0] result;
wire carry;
wire zero;
ALU_4_Bit behav (.a(a),.b(b),.sel(sel),.result(result),.carry(carry),.zero(zero));
integer i;

initial begin
    $dumpfile("ALU_4_Bit.vcd");
    $dumpvars(0,testbench);
       $display(" a    |  b    | sel | result | carry | zero ");
    $display("---------------------------------------------");
for (i=0;i<2048;i=i+1 ) begin
    
    {a,b,sel}=i[10:0];
    #5;
$display(" %b | %b |  %b  |  %b   |   %b   |   %b", a, b, sel, result, carry, zero);

end
$finish;
end

endmodule

Intermediate_Projects/03_ALU_4_Bit/ALU_4_Bit.vcd
$date
	Wed Jun 18 12:00:59 2025
$end
$version
	Icarus Verilog
$end
$timescale
	1ns
$end
$scope module testbench $end
$var wire 1 ! carry $end
$var wire 4 " result [3:0] $end
$var wire 1 # zero $end
$var reg 4 $ a [3:0] $end
$var reg 4 % b [3:0] $end
$var integer 32 & i [31:0] $end
$var reg 3 ' sel [2:0] $end
$scope module behav $end
$var wire 4 ( a [3:0] $end
$var wire 4 ) b [3:0] $end
$var wire 3 * sel [2:0] $end
$var reg 1 + carry $end
$var reg 4 , result [3:0] $end
$var reg 5 - temp [4:0] $end
$var reg 1 . zero $end
$upscope $end
$upscope $end
$enddefinitions $end
#0
$dumpvars
1.
b0 -
b0 ,
0+
b0 *
b0 )
b0 (
b0 '
b0 &
b0 %
b0 $
1#
b0 "
0!
$end
#5
b1 '
b1 *
b1 &
#10
b10 '
b10 *
b10 &
#15
b11 '
b11 *
b11 &
#20
b100 '
b100 *
b100 &
#25
0.
0#
b1111 ,
b1111 "
b101 '
b101 *
b101 &
#30
1.
1#
b0 ,
b0 "
b110 '
b110 *
b110 &
#35
b111 '
b111 *
b111 &
#40
0.
0#
b1 ,
b1 "
b1 -
b1 %
b1 )
b0 '
b0 *
b1000 &
#45
1+
1!
b11111 -
b1111 ,
b1111 "
b1 '
b1 *
b1001 &
#50
1.
1#
b0 ,
b0 "
b10 '
b10 *
b1010 &
#55
0.
0#
b1 ,
b1 "
b11 '
b11 *
b1011 &
#60
b100 '
b100 *
b1100 &
#65
b1111 ,
b1111 "
b101 '
b101 *
b1101 &
#70
1.
1#
b0 ,
b0 "
b110 '
b110 *
b1110 &
#75
b111 '
b111 *
b1111 &
#80
0.
0#
0+
0!
b10 ,
b10 "
b10 -
b10 %
b10 )
b0 '
b0 *
b10000 &
#85
1+
1!
b11110 -
b1110 ,
b1110 "
b1 '
b1 *
b10001 &
#90
1.
1#
b0 ,
b0 "
b10 '
b10 *
b10010 &
#95
0.
0#
b10 ,
b10 "
b11 '
b11 *
b10011 &
#100
b100 '
b100 *
b10100 &
#105
b1111 ,
b1111 "
b101 '
b101 *
b10101 &
#110
1.
1#
b0 ,
b0 "
b110 '
b110 *
b10110 &
#115
b111 '
b111 *
b10111 &
#120
0.
0#
0+
0!
b11 ,
b11 "
b11 -
b11 %
b11 )
b0 '
b0 *
b11000 &
#125
1+
1!
b11101 -
b1101 ,
b1101 "
b1 '
b1 *
b11001 &
#130
1.
1#
b0 ,
b0 "
b10 '
b10 *
b11010 &
#135
0.
0#
b11 ,
b11 "
b11 '
b11 *
b11011 &
#140
b100 '
b100 *
b11100 &
#145
b1111 ,
b1111 "
b101 '
b101 *
b11101 &
#150
1.
1#
b0 ,
b0 "
b110 '
b110 *
b11110 &
#155
b111 '
b111 *
b11111 &
#160
0.
0#
0+
0!
b100 ,
b100 "
b100 -
b100 %
b100 )
b0 '
b0 *
b100000 &
#165
1+
1!
b11100 -
b1100 ,
b1100 "
b1 '
b1 *
b100001 &
#170
1.
1#
b0 ,
b0 "
b10 '
b10 *
b100010 &
#175
0.
0#
b100 ,
b100 "
b11 '
b11 *
b100011 &
#180
b100 '
b100 *
b100100 &
#185
b1111 ,
b1111 "
b101 '
b101 *
b100101 &
#190
1.
1#
b0 ,
b0 "
b110 '
b110 *
b100110 &
#195
b111 '
b111 *
b100111 &
#200
0.
0#
0+
0!
b101 ,
b101 "
b101 -
b101 %
b101 )
b0 '
b0 *
b101000 &
#205
1+
1!
b11011 -
b1011 ,
b1011 "
b1 '
b1 *
b101001 &
#210
1.
1#
b0 ,
b0 "
b10 '
b10 *
b101010 &
#215
0.
0#
b101 ,
b101 "
b11 '
b11 *
b101011 &
#220
b100 '
b100 *
b101100 &
#225
b1111 ,
b1111 "
b101 '
b101 *
b101101 &
#230
1.
1#
b0 ,
b0 "
b110 '
b110 *
b101110 &
#235
b111 '
b111 *
b101111 &
#240
0.
0#
0+
0!
b110 ,
b110 "
b110 -
b110 %
b110 )
b0 '
b0 *
b110000 &
#245
1+
1!
b11010 -
b1010 ,
b1010 "
b1 '
b1 *
b110001 &
#250
1.
1#
b0 ,
b0 "
b10 '
b10 *
b110010 &
#255
0.
0#
b110 ,
b110 "
b11 '
b11 *
b110011 &
#260
b100 '
b100 *
b110100 &
#265
b1111 ,
b1111 "
b101 '
b101 *
b110101 &
#270
1.
1#
b0 ,
b0 "
b110 '
b110 *
b110110 &
#275
b111 '
b111 *
b110111 &
#280
0.
0#
0+
0!
b111 ,
b111 "
b111 -
b111 %
b111 )
b0 '
b0 *
b111000 &
#285
1+
1!
b11001 -
b1001 ,
b1001 "
b1 '
b1 *
b111001 &
#290
1.
1#
b0 ,
b0 "
b10 '
b10 *
b111010 &
#295
0.
0#
b111 ,
b111 "
b11 '
b11 *
b111011 &
#300
b100 '
b100 *
b111100 &
#305
b1111 ,
b1111 "
b101 '
b101 *
b111101 &
#310
1.
1#
b0 ,
b0 "
b110 '
b110 *
b111110 &
#315
b111 '
b111 *
b111111 &
#320
0.
0#
0+
0!
b1000 ,
b1000 "
b1000 -
b1000 %
b1000 )
b0 '
b0 *
b1000000 &
#325
1+
1!
b11000 -
b1 '
b1 *
b1000001 &
#330
1.
1#
b0 ,
b0 "
b10 '
b10 *
b1000010 &
#335
0.
0#
b1000 ,
b1000 "
b11 '
b11 *
b1000011 &
#340
b100 '
b100 *
b1000100 &
#345
b1111 ,
b1111 "
b101 '
b101 *
b1000101 &
#350
1.
1#
b0 ,
b0 "
b110 '
b110 *
b1000110 &
#355
b111 '
b111 *
b1000111 &
#360
0.
0#
0+
0!
b1001 ,
b1001 "
b1001 -
b1001 %
b1001 )
b0 '
b0 *
b1001000 &
#365
1+
1!
b10111 -
b111 ,
b111 "
b1 '
b1 *
b1001001 &
#370
1.
1#
b0 ,
b0 "
b10 '
b10 *
b1001010 &
#375
0.
0#
b1001 ,
b1001 "
b11 '
b11 *
b1001011 &
#380
b100 '
b100 *
b1001100 &
#385
b1111 ,
b1111 "
b101 '
b101 *
b1001101 &
#390
1.
1#
b0 ,
b0 "
b110 '
b110 *
b1001110 &
#395
b111 '
b111 *
b1001111 &
#400
0.
0#
0+
0!
b1010 ,
b1010 "
b1010 -
b1010 %
b1010 )
b0 '
b0 *
b1010000 &
#405
1+
1!
b10110 -
b110 ,
b110 "
b1 '
b1 *
b1010001 &
#410
1.
1#
b0 ,
b0 "
b10 '
b10 *
b1010010 &
#415
0.
0#
b1010 ,
b1010 "
b11 '
b11 *
b1010011 &
#420
b100 '
b100 *
b1010100 &
#425
b1111 ,
b1111 "
b101 '
b101 *
b1010101 &
#430
1.
1#
b0 ,
b0 "
b110 '
b110 *
b1010110 &
#435
b111 '
b111 *
b1010111 &
#440
0.
0#
0+
0!
b1011 ,
b1011 "
b1011 -
b1011 %
b1011 )
b0 '
b0 *
b1011000 &
#445
1+
1!
b10101 -
b101 ,
b101 "
b1 '
b1 *
b1011001 &
#450
1.
1#
b0 ,
b0 "
b10 '
b10 *
b1011010 &
#455
0.
0#
b1011 ,
b1011 "
b11 '
b11 *
b1011011 &
#460
b100 '
b100 *
b1011100 &
#465
b1111 ,
b1111 "
b101 '
b101 *
b1011101 &
#470
1.
1#
b0 ,
b0 "
b110 '
b110 *
b1011110 &
#475
b111 '
b111 *
b1011111 &
#480
0.
0#
0+
0!
b1100 ,
b1100 "
b1100 -
b1100 %
b1100 )
b0 '
b0 *
b1100000 &
#485
1+
1!
b10100 -
b100 ,
b100 "
b1 '
b1 *
b1100001 &
#490
1.
1#
b0 ,
b0 "
b10 '
b10 *
b1100010 &
#495
0.
0#
b1100 ,
b1100 "
b11 '
b11 *
b1100011 &
#500
b100 '
b100 *
b1100100 &
#505
b1111 ,
b1111 "
b101 '
b101 *
b1100101 &
#510
1.
1#
b0 ,
b0 "
b110 '
b110 *
b1100110 &
#515
b111 '
b111 *
b1100111 &
#520
0.
0#
0+
0!
b1101 ,
b1101 "
b1101 -
b1101 %
b1101 )
b0 '
b0 *
b1101000 &
#525
1+
1!
b10011 -
b11 ,
b11 "
b1 '
b1 *
b1101001 &
#530
1.
1#
b0 ,
b0 "
b10 '
b10 *
b1101010 &
#535
0.
0#
b1101 ,
b1101 "
b11 '
b11 *
b1101011 &
#540
b100 '
b100 *
b1101100 &
#545
b1111 ,
b1111 "
b101 '
b101 *
b1101101 &
#550
1.
1#
b0 ,
b0 "
b110 '
b110 *
b1101110 &
#555
b111 '
b111 *
b1101111 &
#560
0.
0#
0+
0!
b1110 ,
b1110 "
b1110 -
b1110 %
b1110 )
b0 '
b0 *
b1110000 &
#565
1+
1!
b10010 -
b10 ,
b10 "
b1 '
b1 *
b1110001 &
#570
1.
1#
b0 ,
b0 "
b10 '
b10 *
b1110010 &
#575
0.
0#
b1110 ,
b1110 "
b11 '
b11 *
b1110011 &
#580
b100 '
b100 *
b1110100 &
#585
b1111 ,
b1111 "
b101 '
b101 *
b1110101 &
#590
1.
1#
b0 ,
b0 "
b110 '
b110 *
b1110110 &
#595
b111 '
b111 *
b1110111 &
#600
0.
0#
0+
0!
b1111 ,
b1111 "
b1111 -
b1111 %
b1111 )
b0 '
b0 *
b1111000 &
#605
1+
1!
b10001 -
b1 ,
b1 "
b1 '
b1 *
b1111001 &
#610
1.
1#
b0 ,
b0 "
b10 '
b10 *
b1111010 &
#615
0.
0#
b1111 ,
b1111 "
b11 '
b11 *
b1111011 &
#620
b100 '
b100 *
b1111100 &
#625
b101 '
b101 *
b1111101 &
#630
1.
1#
b0 ,
b0 "
b110 '
b110 *
b1111110 &
#635
b111 '
b111 *
b1111111 &
#640
0.
0#
0+
0!
b1 ,
b1 "
b1 -
b1 $
b1 (
b0 %
b0 )
b0 '
b0 *
b10000000 &
#645
b1 '
b1 *
b10000001 &
#650
1.
1#
b0 ,
b0 "
b10 '
b10 *
b10000010 &
#655
0.
0#
b1 ,
b1 "
b11 '
b11 *
b10000011 &
#660
b100 '
b100 *
b10000100 &
#665
b1110 ,
b1110 "
b101 '
b101 *
b10000101 &
#670
b10 ,
b10 "
b110 '
b110 *
b10000110 &
#675
1.
1#
b0 ,
b0 "
b111 '
b111 *
b10000111 &
#680
0.
0#
b10 ,
b10 "
b10 -
b1 %
b1 )
b0 '
b0 *
b10001000 &
#685
1.
1#
b0 -
b0 ,
b0 "
b1 '
b1 *
b10001001 &
#690
0.
0#
b1 ,
b1 "
b10 '
b10 *
b10001010 &
#695
b11 '
b11 *
b10001011 &
#700
1.
1#
b0 ,
b0 "
b100 '
b100 *
b10001100 &
#705
0.
0#
b1110 ,
b1110 "
b101 '
b101 *
b10001101 &
#710
b10 ,
b10 "
b110 '
b110 *
b10001110 &
#715
1.
1#
b0 ,
b0 "
b111 '
b111 *
b10001111 &
#720
0.
0#
b11 ,
b11 "
b11 -
b10 %
b10 )
b0 '
b0 *
b10010000 &
#725
1+
1!
b11111 -
b1111 ,
b1111 "
b1 '
b1 *
b10010001 &
#730
1.
1#
b0 ,
b0 "
b10 '
b10 *
b10010010 &
#735
0.
0#
b11 ,
b11 "
b11 '
b11 *
b10010011 &
#740
b100 '
b100 *
b10010100 &
#745
b1110 ,
b1110 "
b101 '
b101 *
b10010101 &
#750
b10 ,
b10 "
b110 '
b110 *
b10010110 &
#755
1.
1#
b0 ,
b0 "
b111 '
b111 *
b10010111 &
#760
0.
0#
0+
0!
b100 ,
b100 "
b100 -
b11 %
b11 )
b0 '
b0 *
b10011000 &
#765
1+
1!
b11110 -
b1110 ,
b1110 "
b1 '
b1 *
b10011001 &
#770
b1 ,
b1 "
b10 '
b10 *
b10011010 &
#775
b11 ,
b11 "
b11 '
b11 *
b10011011 &
#780
b10 ,
b10 "
b100 '
b100 *
b10011100 &
#785
b1110 ,
b1110 "
b101 '
b101 *
b10011101 &
#790
b10 ,
b10 "
b110 '
b110 *
b10011110 &
#795
1.
1#
b0 ,
b0 "
b111 '
b111 *
b10011111 &
#800
0.
0#
0+
0!
b101 ,
b101 "
b101 -
b100 %
b100 )
b0 '
b0 *
b10100000 &
#805
1+
1!
b11101 -
b1101 ,
b1101 "
b1 '
b1 *
b10100001 &
#810
1.
1#
b0 ,
b0 "
b10 '
b10 *
b10100010 &
#815
0.
0#
b101 ,
b101 "
b11 '
b11 *
b10100011 &
#820
b100 '
b100 *
b10100100 &
#825
b1110 ,
b1110 "
b101 '
b101 *
b10100101 &
#830
b10 ,
b10 "
b110 '
b110 *
b10100110 &
#835
1.
1#
b0 ,
b0 "
b111 '
b111 *
b10100111 &
#840
0.
0#
0+
0!
b110 ,
b110 "
b110 -
b101 %
b101 )
b0 '
b0 *
b10101000 &
#845
1+
1!
b11100 -
b1100 ,
b1100 "
b1 '
b1 *
b10101001 &
#850
b1 ,
b1 "
b10 '
b10 *
b10101010 &
#855
b101 ,
b101 "
b11 '
b11 *
b10101011 &
#860
b100 ,
b100 "
b100 '
b100 *
b10101100 &
#865
b1110 ,
b1110 "
b101 '
b101 *
b10101101 &
#870
b10 ,
b10 "
b110 '
b110 *
b10101110 &
#875
1.
1#
b0 ,
b0 "
b111 '
b111 *
b10101111 &
#880
0.
0#
0+
0!
b111 ,
b111 "
b111 -
b110 %
b110 )
b0 '
b0 *
b10110000 &
#885
1+
1!
b11011 -
b1011 ,
b1011 "
b1 '
b1 *
b10110001 &
#890
1.
1#
b0 ,
b0 "
b10 '
b10 *
b10110010 &
#895
0.
0#
b111 ,
b111 "
b11 '
b11 *
b10110011 &
#900
b100 '
b100 *
b10110100 &
#905
b1110 ,
b1110 "
b101 '
b101 *
b10110101 &
#910
b10 ,
b10 "
b110 '
b110 *
b10110110 &
#915
1.
1#
b0 ,
b0 "
b111 '
b111 *
b10110111 &
#920
0.
0#
0+
0!
b1000 ,
b1000 "
b1000 -
b111 %
b111 )
b0 '
b0 *
b10111000 &
#925
1+
1!
b11010 -
b1010 ,
b1010 "
b1 '
b1 *
b10111001 &
#930
b1 ,
b1 "
b10 '
b10 *
b10111010 &
#935
b111 ,
b111 "
b11 '
b11 *
b10111011 &
#940
b110 ,
b110 "
b100 '
b100 *
b10111100 &
#945
b1110 ,
b1110 "
b101 '
b101 *
b10111101 &
#950
b10 ,
b10 "
b110 '
b110 *
b10111110 &
#955
1.
1#
b0 ,
b0 "
b111 '
b111 *
b10111111 &
#960
0.
0#
0+
0!
b1001 ,
b1001 "
b1001 -
b1000 %
b1000 )
b0 '
b0 *
b11000000 &
#965
1+
1!
b11001 -
b1 '
b1 *
b11000001 &
#970
1.
1#
b0 ,
b0 "
b10 '
b10 *
b11000010 &
#975
0.
0#
b1001 ,
b1001 "
b11 '
b11 *
b11000011 &
#980
b100 '
b100 *
b11000100 &
#985
b1110 ,
b1110 "
b101 '
b101 *
b11000101 &
#990
b10 ,
b10 "
b110 '
b110 *
b11000110 &
#995
1.
1#
b0 ,
b0 "
b111 '
b111 *
b11000111 &
#1000
0.
0#
0+
0!
b1010 ,
b1010 "
b1010 -
b1001 %
b1001 )
b0 '
b0 *
b11001000 &
#1005
1+
1!
b11000 -
b1000 ,
b1000 "
b1 '
b1 *
b11001001 &
#1010
b1 ,
b1 "
b10 '
b10 *
b11001010 &
#1015
b1001 ,
b1001 "
b11 '
b11 *
b11001011 &
#1020
b1000 ,
b1000 "
b100 '
b100 *
b11001100 &
#1025
b1110 ,
b1110 "
b101 '
b101 *
b11001101 &
#1030
b10 ,
b10 "
b110 '
b110 *
b11001110 &
#1035
1.
1#
b0 ,
b0 "
b111 '
b111 *
b11001111 &
#1040
0.
0#
0+
0!
b1011 ,
b1011 "
b1011 -
b1010 %
b1010 )
b0 '
b0 *
b11010000 &
#1045
1+
1!
b10111 -
b111 ,
b111 "
b1 '
b1 *
b11010001 &
#1050
1.
1#
b0 ,
b0 "
b10 '
b10 *
b11010010 &
#1055
0.
0#
b1011 ,
b1011 "
b11 '
b11 *
b11010011 &
#1060
b100 '
b100 *
b11010100 &
#1065
b1110 ,
b1110 "
b101 '
b101 *
b11010101 &
#1070
b10 ,
b10 "
b110 '
b110 *
b11010110 &
#1075
1.
1#
b0 ,
b0 "
b111 '
b111 *
b11010111 &
#1080
0.
0#
0+
0!
b1100 ,
b1100 "
b1100 -
b1011 %
b1011 )
b0 '
b0 *
b11011000 &
#1085
1+
1!
b10110 -
b110 ,
b110 "
b1 '
b1 *
b11011001 &
#1090
b1 ,
b1 "
b10 '
b10 *
b11011010 &
#1095
b1011 ,
b1011 "
b11 '
b11 *
b11011011 &
#1100
b1010 ,
b1010 "
b100 '
b100 *
b11011100 &
#1105
b1110 ,
b1110 "
b101 '
b101 *
b11011101 &
#1110
b10 ,
b10 "
b110 '
b110 *
b11011110 &
#1115
1.
1#
b0 ,
b0 "
b111 '
b111 *
b11011111 &
#1120
0.
0#
0+
0!
b1101 ,
b1101 "
b1101 -
b1100 %
b1100 )
b0 '
b0 *
b11100000 &
#1125
1+
1!
b10101 -
b101 ,
b101 "
b1 '
b1 *
b11100001 &
#1130
1.
1#
b0 ,
b0 "
b10 '
b10 *
b11100010 &
#1135
0.
0#
b1101 ,
b1101 "
b11 '
b11 *
b11100011 &
#1140
b100 '
b100 *
b11100100 &
#1145
b1110 ,
b1110 "
b101 '
b101 *
b11100101 &
#1150
b10 ,
b10 "
b110 '
b110 *
b11100110 &
#1155
1.
1#
b0 ,
b0 "
b111 '
b111 *
b11100111 &
#1160
0.
0#
0+
0!
b1110 ,
b1110 "
b1110 -
b1101 %
b1101 )
b0 '
b0 *
b11101000 &
#1165
1+
1!
b10100 -
b100 ,
b100 "
b1 '
b1 *
b11101001 &
#1170
b1 ,
b1 "
b10 '
b10 *
b11101010 &
#1175
b1101 ,
b1101 "
b11 '
b11 *
b11101011 &
#1180
b1100 ,
b1100 "
b100 '
b100 *
b11101100 &
#1185
b1110 ,
b1110 "
b101 '
b101 *
b11101101 &
#1190
b10 ,
b10 "
b110 '
b110 *
b11101110 &
#1195
1.
1#
b0 ,
b0 "
b111 '
b111 *
b11101111 &
#1200
0.
0#
0+
0!
b1111 ,
b1111 "
b1111 -
b1110 %
b1110 )
b0 '
b0 *
b11110000 &
#1205
1+
1!
b10011 -
b11 ,
b11 "
b1 '
b1 *
b11110001 &
#1210
1.
1#
b0 ,
b0 "
b10 '
b10 *
b11110010 &
#1215
0.
0#
b1111 ,
b1111 "
b11 '
b11 *
b11110011 &
#1220
b100 '
b100 *
b11110100 &
#1225
b1110 ,
b1110 "
b101 '
b101 *
b11110101 &
#1230
b10 ,
b10 "
b110 '
b110 *
b11110110 &
#1235
1.
1#
b0 ,
b0 "
b111 '
b111 *
b11110111 &
#1240
b10000 -
b1111 %
b1111 )
b0 '
b0 *
b11111000 &
#1245
0.
0#
b10010 -
b10 ,
b10 "
b1 '
b1 *
b11111001 &
#1250
b1 ,
b1 "
b10 '
b10 *
b11111010 &
#1255
b1111 ,
b1111 "
b11 '
b11 *
b11111011 &
#1260
b1110 ,
b1110 "
b100 '
b100 *
b11111100 &
#1265
b101 '
b101 *
b11111101 &
#1270
b10 ,
b10 "
b110 '
b110 *
b11111110 &
#1275
1.
1#
b0 ,
b0 "
b111 '
b111 *
b11111111 &
#1280
0.
0#
0+
0!
b10 ,
b10 "
b10 -
b10 $
b10 (
b0 %
b0 )
b0 '
b0 *
b100000000 &
#1285
b1 '
b1 *
b100000001 &
#1290
1.
1#
b0 ,
b0 "
b10 '
b10 *
b100000010 &
#1295
0.
0#
b10 ,
b10 "
b11 '
b11 *
b100000011 &
#1300
b100 '
b100 *
b100000100 &
#1305
b1101 ,
b1101 "
b101 '
b101 *
b100000101 &
#1310
b100 ,
b100 "
b110 '
b110 *
b100000110 &
#1315
b1 ,
b1 "
b111 '
b111 *
b100000111 &
#1320
b11 ,
b11 "
b11 -
b1 %
b1 )
b0 '
b0 *
b100001000 &
#1325
b1 -
b1 ,
b1 "
b1 '
b1 *
b100001001 &
#1330
1.
1#
b0 ,
b0 "
b10 '
b10 *
b100001010 &
#1335
0.
0#
b11 ,
b11 "
b11 '
b11 *
b100001011 &
#1340
b100 '
b100 *
b100001100 &
#1345
b1101 ,
b1101 "
b101 '
b101 *
b100001101 &
#1350
b100 ,
b100 "
b110 '
b110 *
b100001110 &
#1355
b1 ,
b1 "
b111 '
b111 *
b100001111 &
#1360
b100 ,
b100 "
b100 -
b10 %
b10 )
b0 '
b0 *
b100010000 &
#1365
1.
1#
b0 -
b0 ,
b0 "
b1 '
b1 *
b100010001 &
#1370
0.
0#
b10 ,
b10 "
b10 '
b10 *
b100010010 &
#1375
b11 '
b11 *
b100010011 &
#1380
1.
1#
b0 ,
b0 "
b100 '
b100 *
b100010100 &
#1385
0.
0#
b1101 ,
b1101 "
b101 '
b101 *
b100010101 &
#1390
b100 ,
b100 "
b110 '
b110 *
b100010110 &
#1395
b1 ,
b1 "
b111 '
b111 *
b100010111 &
#1400
b101 ,
b101 "
b101 -
b11 %
b11 )
b0 '
b0 *
b100011000 &
#1405
1+
1!
b11111 -
b1111 ,
b1111 "
b1 '
b1 *
b100011001 &
#1410
b10 ,
b10 "
b10 '
b10 *
b100011010 &
#1415
b11 ,
b11 "
b11 '
b11 *
b100011011 &
#1420
b1 ,
b1 "
b100 '
b100 *
b100011100 &
#1425
b1101 ,
b1101 "
b101 '
b101 *
b100011101 &
#1430
b100 ,
b100 "
b110 '
b110 *
b100011110 &
#1435
b1 ,
b1 "
b111 '
b111 *
b100011111 &
#1440
0+
0!
b110 ,
b110 "
b110 -
b100 %
b100 )
b0 '
b0 *
b100100000 &
#1445
1+
1!
b11110 -
b1110 ,
b1110 "
b1 '
b1 *
b100100001 &
#1450
1.
1#
b0 ,
b0 "
b10 '
b10 *
b100100010 &
#1455
0.
0#
b110 ,
b110 "
b11 '
b11 *
b100100011 &
#1460
b100 '
b100 *
b100100100 &
#1465
b1101 ,
b1101 "
b101 '
b101 *
b100100101 &
#1470
b100 ,
b100 "
b110 '
b110 *
b100100110 &
#1475
b1 ,
b1 "
b111 '
b111 *
b100100111 &
#1480
0+
0!
b111 ,
b111 "
b111 -
b101 %
b101 )
b0 '
b0 *
b100101000 &
#1485
1+
1!
b11101 -
b1101 ,
b1101 "
b1 '
b1 *
b100101001 &
#1490
1.
1#
b0 ,
b0 "
b10 '
b10 *
b100101010 &
#1495
0.
0#
b111 ,
b111 "
b11 '
b11 *
b100101011 &
#1500
b100 '
b100 *
b100101100 &
#1505
b1101 ,
b1101 "
b101 '
b101 *
b100101101 &
#1510
b100 ,
b100 "
b110 '
b110 *
b100101110 &
#1515
b1 ,
b1 "
b111 '
b111 *
b100101111 &
#1520
0+
0!
b1000 ,
b1000 "
b1000 -
b110 %
b110 )
b0 '
b0 *
b100110000 &
#1525
1+
1!
b11100 -
b1100 ,
b1100 "
b1 '
b1 *
b100110001 &
#1530
b10 ,
b10 "
b10 '
b10 *
b100110010 &
#1535
b110 ,
b110 "
b11 '
b11 *
b100110011 &
#1540
b100 ,
b100 "
b100 '
b100 *
b100110100 &
#1545
b1101 ,
b1101 "
b101 '
b101 *
b100110101 &
#1550
b100 ,
b100 "
b110 '
b110 *
b100110110 &
#1555
b1 ,
b1 "
b111 '
b111 *
b100110111 &
#1560
0+
0!
b1001 ,
b1001 "
b1001 -
b111 %
b111 )
b0 '
b0 *
b100111000 &
#1565
1+
1!
b11011 -
b1011 ,
b1011 "
b1 '
b1 *
b100111001 &
#1570
b10 ,
b10 "
b10 '
b10 *
b100111010 &
#1575
b111 ,
b111 "
b11 '
b11 *
b100111011 &
#1580
b101 ,
b101 "
b100 '
b100 *
b100111100 &
#1585
b1101 ,
b1101 "
b101 '
b101 *
b100111101 &
#1590
b100 ,
b100 "
b110 '
b110 *
b100111110 &
#1595
b1 ,
b1 "
b111 '
b111 *
b100111111 &
#1600
0+
0!
b1010 ,
b1010 "
b1010 -
b1000 %
b1000 )
b0 '
b0 *
b101000000 &
#1605
1+
1!
b11010 -
b1 '
b1 *
b101000001 &
#1610
1.
1#
b0 ,
b0 "
b10 '
b10 *
b101000010 &
#1615
0.
0#
b1010 ,
b1010 "
b11 '
b11 *
b101000011 &
#1620
b100 '
b100 *
b101000100 &
#1625
b1101 ,
b1101 "
b101 '
b101 *
b101000101 &
#1630
b100 ,
b100 "
b110 '
b110 *
b101000110 &
#1635
b1 ,
b1 "
b111 '
b111 *
b101000111 &
#1640
0+
0!
b1011 ,
b1011 "
b1011 -
b1001 %
b1001 )
b0 '
b0 *
b101001000 &
#1645
1+
1!
b11001 -
b1001 ,
b1001 "
b1 '
b1 *
b101001001 &
#1650
1.
1#
b0 ,
b0 "
b10 '
b10 *
b101001010 &
#1655
0.
0#
b1011 ,
b1011 "
b11 '
b11 *
b101001011 &
#1660
b100 '
b100 *
b101001100 &
#1665
b1101 ,
b1101 "
b101 '
b101 *
b101001101 &
#1670
b100 ,
b100 "
b110 '
b110 *
b101001110 &
#1675
b1 ,
b1 "
b111 '
b111 *
b101001111 &
#1680
0+
0!
b1100 ,
b1100 "
b1100 -
b1010 %
b1010 )
b0 '
b0 *
b101010000 &
#1685
1+
1!
b11000 -
b1000 ,
b1000 "
b1 '
b1 *
b101010001 &
#1690
b10 ,
b10 "
b10 '
b10 *
b101010010 &
#1695
b1010 ,
b1010 "
b11 '
b11 *
b101010011 &
#1700
b1000 ,
b1000 "
b100 '
b100 *
b101010100 &
#1705
b1101 ,
b1101 "
b101 '
b101 *
b101010101 &
#1710
b100 ,
b100 "
b110 '
b110 *
b101010110 &
#1715
b1 ,
b1 "
b111 '
b111 *
b101010111 &
#1720
0+
0!
b1101 ,
b1101 "
b1101 -
b1011 %
b1011 )
b0 '
b0 *
b101011000 &
#1725
1+
1!
b10111 -
b111 ,
b111 "
b1 '
b1 *
b101011001 &
#1730
b10 ,
b10 "
b10 '
b10 *
b101011010 &
#1735
b1011 ,
b1011 "
b11 '
b11 *
b101011011 &
#1740
b1001 ,
b1001 "
b100 '
b100 *
b101011100 &
#1745
b1101 ,
b1101 "
b101 '
b101 *
b101011101 &
#1750
b100 ,
b100 "
b110 '
b110 *
b101011110 &
#1755
b1 ,
b1 "
b111 '
b111 *
b101011111 &
#1760
0+
0!
b1110 ,
b1110 "
b1110 -
b1100 %
b1100 )
b0 '
b0 *
b101100000 &
#1765
1+
1!
b10110 -
b110 ,
b110 "
b1 '
b1 *
b101100001 &
#1770
1.
1#
b0 ,
b0 "
b10 '
b10 *
b101100010 &
#1775
0.
0#
b1110 ,
b1110 "
b11 '
b11 *
b101100011 &
#1780
b100 '
b100 *
b101100100 &
#1785
b1101 ,
b1101 "
b101 '
b101 *
b101100101 &
#1790
b100 ,
b100 "
b110 '
b110 *
b101100110 &
#1795
b1 ,
b1 "
b111 '
b111 *
b101100111 &
#1800
0+
0!
b1111 ,
b1111 "
b1111 -
b1101 %
b1101 )
b0 '
b0 *
b101101000 &
#1805
1+
1!
b10101 -
b101 ,
b101 "
b1 '
b1 *
b101101001 &
#1810
1.
1#
b0 ,
b0 "
b10 '
b10 *
b101101010 &
#1815
0.
0#
b1111 ,
b1111 "
b11 '
b11 *
b101101011 &
#1820
b100 '
b100 *
b101101100 &
#1825
b1101 ,
b1101 "
b101 '
b101 *
b101101101 &
#1830
b100 ,
b100 "
b110 '
b110 *
b101101110 &
#1835
b1 ,
b1 "
b111 '
b111 *
b101101111 &
#1840
1.
1#
b0 ,
b0 "
b10000 -
b1110 %
b1110 )
b0 '
b0 *
b101110000 &
#1845
0.
0#
b10100 -
b100 ,
b100 "
b1 '
b1 *
b101110001 &
#1850
b10 ,
b10 "
b10 '
b10 *
b101110010 &
#1855
b1110 ,
b1110 "
b11 '
b11 *
b101110011 &
#1860
b1100 ,
b1100 "
b100 '
b100 *
b101110100 &
#1865
b1101 ,
b1101 "
b101 '
b101 *
b101110101 &
#1870
b100 ,
b100 "
b110 '
b110 *
b101110110 &
#1875
b1 ,
b1 "
b111 '
b111 *
b101110111 &
#1880
b10001 -
b1111 %
b1111 )
b0 '
b0 *
b101111000 &
#1885
b10011 -
b11 ,
b11 "
b1 '
b1 *
b101111001 &
#1890
b10 ,
b10 "
b10 '
b10 *
b101111010 &
#1895
b1111 ,
b1111 "
b11 '
b11 *
b101111011 &
#1900
b1101 ,
b1101 "
b100 '
b100 *
b101111100 &
#1905
b101 '
b101 *
b101111101 &
#1910
b100 ,
b100 "
b110 '
b110 *
b101111110 &
