04_4to1_Mux/mux_4to1_behavioural.v
module mux_4to1_behavioural(input i0,i1,i2,i3,s0,s1,E, output reg Y);// Output must be reg because it's driven inside an always block adn wire cannot store any value

always@(*)begin
if(E==0)
Y=0;
else begin
case({s0,s1})
  2'b00: Y = i0;
  2'b01: Y = i1;
  2'b10: Y = i2;
  2'b11: Y = i3;
default: Y = 0;
endcase
 end
end
endmodule

04_4to1_Mux/mux_4to1_gatelevel.v
module mux_4to1_gatelevel(input i0,i1,i2,i3,s0,s1,E, output Y,w0,w1,w2,w3,w4);

wire s0_not,s1_not;
not g0(s0_not,s0);
not g1(s1_not,s1);
and g2(w0,s0_not,s1_not,i0);
and g3(w1,s0,s1_not,i1);
and g4(w2,s0_not,s1,i2);
and g5(w3,s0,s1,i3);
or  g6(w4,w0,w1,w2,w3);
and g7(Y,w4,E);

endmodule

basic_projects/04_4to1_Mux/testbench.v
`timescale 1ns/1ns

module  testbench;
reg i0,i1,i2,i3,s0,s1,E;
wire Y_behav,w0_behav,w1_behav,w2_behav,w3_behav,w4_behav,Y_gate,w0_gate,w1_gate,w2_gate,w3_gate,w4_gate;
integer i;
mux_4to1_gatelevel gate(.i0(i0),.i1(i1),.i2(i2),.i3(i3),.s0(s0),.s1(s1),.E(E),.Y(Y_gate),.w0(w0_gate),.w1(w1_gate),.w2(w2_gate),.w3(w3_gate),.w4(w4_gate));


mux_4to1_behavioural behav(.i0(i0),.i1(i1),.i2(i2),.i3(i3),.s0(s0),.s1(s1),.E(E),.Y(Y_behav));

initial begin 
$dumpfile("mux_4to1.vcd");
$dumpvars(0,testbench);

E=0;
i0=1'bx;
i1=1'bx;
i2=1'bx;
i3=1'bx;
s0=1'bx;
s1=1'bx;
#10;
$display("E=0 -> Y_gate=%b, Y_behav=%b (Expected: 0)", Y_gate, Y_behav);
E=1;
for(i=0;i<64;i=i+1)begin
{i0,i1,i2,i3,s0,s1}=i[5:0];
#10
$display("i0=%b,i1=%b,i2=%b,i3=%b,s0=%b,s1=%b,E=%b,Y_gate=%b,Y_behav=%b",i0,i1,i2,i3,s0,s1,E,Y_gate,Y_behav);
end
$finish;

end 
endmodule

basic_projects/04_4to1_Mux/mux_4to1.vcd
$date
	Mon Jun 16 17:03:41 2025
$end
$version
	Icarus Verilog
$end
$timescale
	1ps
$end
$scope module testbench $end
$var wire 1 ! Y_behav $end
$var wire 1 " Y_gate $end
$var wire 1 # w0_gate $end
$var wire 1 $ w1_gate $end
$var wire 1 % w2_gate $end
$var wire 1 & w3_gate $end
$var wire 1 ' w4_gate $end
$var reg 1 ( E $end
$var integer 32 ) i [31:0] $end
$var reg 1 * i0 $end
$var reg 1 + i1 $end
$var reg 1 , i2 $end
$var reg 1 - i3 $end
$var reg 1 . s0 $end
$var reg 1 / s1 $end
$scope module gate $end
$var wire 1 0 E $end
$var wire 1 " Y $end
$var wire 1 1 i0 $end
$var wire 1 2 i1 $end
$var wire 1 3 i2 $end
$var wire 1 4 i3 $end
$var wire 1 5 s0 $end
$var wire 1 6 s0_not $end
$var wire 1 7 s1 $end
$var wire 1 8 s1_not $end
$var wire 1 # w0 $end
$var wire 1 $ w1 $end
$var wire 1 % w2 $end
$var wire 1 & w3 $end
$var wire 1 ' w4 $end
$upscope $end
$scope module behav $end
$var wire 1 0 E $end
$var wire 1 1 i0 $end
$var wire 1 2 i1 $end
$var wire 1 3 i2 $end
$var wire 1 4 i3 $end
$var wire 1 5 s0 $end
$var wire 1 7 s1 $end
$var reg 1 9 Y $end
$upscope $end
$upscope $end
$enddefinitions $end
#0
$dumpvars
09
x8
x7
x6
x5
x4
x3
x2
x1
00
x/
x.
x-
x,
x+
x*
bx )
0(
z'
x&
x%
x$
x#
0"
0!
$end
#10000
0'
0#
16
0$
18
0%
0&
0"
0*
01
0+
02
0,
03
0-
04
0.
05
0/
07
b0 )
1(
10
#20000
08
1/
17
b1 )
#30000
06
18
1.
15
0/
07
b10 )
#40000
08
1/
17
b11 )
#50000
16
18
1-
14
0.
05
0/
07
b100 )
#60000
08
1/
17
b101 )
#70000
06
18
1.
15
0/
07
b110 )
#80000
1"
1'
08
1&
19
1!
1/
17
b111 )
#90000
0"
0'
16
18
0&
09
0!
1,
13
0-
04
0.
05
0/
07
b1000 )
#100000
1"
1'
08
1%
1/
17
b1001 )
#110000
0"
0'
06
18
0%
19
1!
1.
15
0/
07
b1010 )
#120000
08
09
0!
1/
17
b1011 )
#130000
16
18
1-
14
0.
05
0/
07
b1100 )
#140000
1"
1'
08
1%
1/
17
b1101 )
#150000
0"
0'
06
18
0%
19
1!
1.
15
0/
07
b1110 )
#160000
1"
1'
08
1&
1/
17
b1111 )
#170000
0"
0'
16
18
0&
09
0!
1+
12
0,
03
0-
04
0.
05
0/
07
b10000 )
#180000
08
19
1!
1/
17
b10001 )
#190000
1"
1'
06
1$
18
09
0!
1.
15
0/
07
b10010 )
#200000
0"
0'
0$
08
1/
17
b10011 )
#210000
16
18
1-
14
0.
05
0/
07
b10100 )
#220000
08
19
1!
1/
17
b10101 )
#230000
1"
1'
06
1$
18
09
0!
1.
15
0/
07
b10110 )
#240000
0$
08
1&
19
1!
1/
17
b10111 )
#250000
0"
0'
16
18
0&
09
0!
1,
13
0-
04
0.
05
0/
07
b11000 )
#260000
1"
1'
08
1%
19
1!
1/
17
b11001 )
#270000
06
1$
18
0%
1.
15
0/
07
b11010 )
#280000
0"
0'
0$
08
09
0!
1/
17
b11011 )
#290000
16
18
1-
14
0.
05
0/
07
b11100 )
#300000
1"
1'
08
1%
19
1!
1/
17
b11101 )
#310000
06
1$
18
0%
1.
15
0/
07
b11110 )
#320000
0$
08
1&
1/
17
b11111 )
#330000
1#
16
18
0&
1*
11
0+
02
0,
03
0-
04
0.
05
0/
07
b100000 )
#340000
0"
0'
0#
08
09
0!
1/
17
b100001 )
#350000
06
18
1.
15
0/
07
b100010 )
#360000
08
1/
17
b100011 )
#370000
1"
1'
1#
16
18
19
1!
1-
14
0.
05
0/
07
b100100 )
#380000
0"
0'
0#
08
09
0!
1/
17
b100101 )
#390000
06
18
1.
15
0/
07
b100110 )
#400000
1"
1'
08
1&
19
1!
1/
17
b100111 )
#410000
1"
1#
1'
16
18
0&
1,
13
0-
04
0.
05
0/
07
b101000 )
#420000
0#
08
1%
09
0!
1/
17
b101001 )
#430000
0"
0'
06
18
0%
19
1!
1.
15
0/
07
b101010 )
#440000
08
09
0!
1/
17
b101011 )
#450000
1"
1'
1#
16
18
19
1!
1-
14
0.
05
0/
07
b101100 )
#460000
0#
08
1%
09
0!
1/
17
b101101 )
#470000
0"
0'
06
18
0%
19
1!
1.
15
0/
07
b101110 )
#480000
1"
1'
08
1&
1/
17
b101111 )
#490000
1"
1#
1'
16
18
0&
1+
12
0,
03
0-
04
0.
05
0/
07
b110000 )
#500000
0"
0'
0#
08
1/
17
b110001 )
#510000
1"
1'
06
1$
18
09
0!
1.
15
0/
07
b110010 )
#520000
0"
0'
0$
08
1/
17
b110011 )
#530000
1"
1'
1#
16
18
19
1!
1-
14
0.
05
0/
07
b110100 )
#540000
0"
0'
0#
08
1/
17
b110101 )
#550000
1"
1'
06
1$
18
09
0!
1.
15
0/
07
b110110 )
#560000
0$
08
1&
19
1!
1/
17
b110111 )
#570000
1"
1#
1'
16
18
0&
1,
13
0-
04
0.
05
0/
07
b111000 )
#580000
0#
08
1%
1/
17
b111001 )
#590000
06
1$
18
0%
1.
15
0/
07
b111010 )
#600000
0"
0'
0$
08
09
0!
1/
17
b111011 )
#610000
1"
1'
1#
16
18
19
1!
1-
14
0.
05
0/
07
b111100 )
#620000
0#
08
1%
1/
17
b111101 )
#630000
06
1$
18
0%
1.
15
0/
07
b111110 )
#640000
0$
08
1&
1/
17
b111111 )
#650000
b1000000 )
