basic_projects/10_8to3_Priority_Encoder/Priority_Encoder_8to3_behav.v
module Priority_Encoder_8to3_behav(input i7,i6,i5,i4,i3,i2,i1,i0, output reg [2:0] y);


always @(*) begin
  

         if(i7) y=3'b111; 
         else if (i6) y=3'b110;
         else if (i5) y=3'b101;
         else if (i4) y=3'b100;
         else if (i3) y=3'b011;
         else if (i2) y=3'b010;
         else if (i1) y=3'b001;
         else if (i0) y=3'b000;
         else begin
y=3'bx;
         end
       
   


   
end
 
  
endmodule

basic_projects/10_8to3_Priority_Encoder/testbench.v
`timescale 1ns/1ps

module testbench;

    reg i7,i6,i5,i4,i3,i2,i1,i0;
    wire [2:0] y;
    integer i;

Priority_Encoder_8to3_behav behav(i7,i6,i5,i4,i3,i2,i1,i0,y);

    initial begin

$dumpfile("Priority_Encoder_8to3.vcd");
$dumpvars(0,testbench);
for ( i=0 ;i<256;i=i+1 ) begin
    {i7,i6,i5,i4,i3,i2,i1,i0}=i[7:0];
    #10;
    $display("i7=%b,i6=%b,i5=%b,i4=%b,i3=%b,i2=%b,i1=%b,i0=%b,y[2]=%b,y[1]=%b,y[0]=%b",i7,i6,i5,i4,i3,i2,i1,i0,y[2],y[1],y[0]);
end

        $finish;
   end


endmodule

basic_projects/10_8to3_Priority_Encoder/Priority_Encoder_8to3.vcd
$date
	Tue Jun 17 14:29:53 2025
$end
$version
	Icarus Verilog
$end
$timescale
	1ps
$end
$scope module testbench $end
$var wire 3 ! y [2:0] $end
$var integer 32 " i [31:0] $end
$var reg 1 # i0 $end
$var reg 1 $ i1 $end
$var reg 1 % i2 $end
$var reg 1 & i3 $end
$var reg 1 ' i4 $end
$var reg 1 ( i5 $end
$var reg 1 ) i6 $end
$var reg 1 * i7 $end
$scope module behav $end
$var wire 1 + i0 $end
$var wire 1 , i1 $end
$var wire 1 - i2 $end
$var wire 1 . i3 $end
$var wire 1 / i4 $end
$var wire 1 0 i5 $end
$var wire 1 1 i6 $end
$var wire 1 2 i7 $end
$var reg 3 3 y [2:0] $end
$upscope $end
$upscope $end
$enddefinitions $end
#0
$dumpvars
bx 3
02
01
00
0/
0.
0-
0,
0+
0*
0)
0(
0'
0&
0%
0$
0#
b0 "
bx !
$end
#10000
b0 3
b0 !
1#
1+
b1 "
#20000
b1 3
b1 !
1$
1,
0#
0+
b10 "
#30000
1#
1+
b11 "
#40000
b10 3
b10 !
1%
1-
0$
0,
0#
0+
b100 "
#50000
1#
1+
b101 "
#60000
1$
1,
0#
0+
b110 "
#70000
1#
1+
b111 "
#80000
b11 3
b11 !
1&
1.
0%
0-
0$
0,
0#
0+
b1000 "
#90000
1#
1+
b1001 "
#100000
1$
1,
0#
0+
b1010 "
#110000
1#
1+
b1011 "
#120000
1%
1-
0$
0,
0#
0+
b1100 "
#130000
1#
1+
b1101 "
#140000
1$
1,
0#
0+
b1110 "
#150000
1#
1+
b1111 "
#160000
b100 3
b100 !
1'
1/
0&
0.
0%
0-
0$
0,
0#
0+
b10000 "
#170000
1#
1+
b10001 "
#180000
1$
1,
0#
0+
b10010 "
#190000
1#
1+
b10011 "
#200000
1%
1-
0$
0,
0#
0+
b10100 "
#210000
1#
1+
b10101 "
#220000
1$
1,
0#
0+
b10110 "
#230000
1#
1+
b10111 "
#240000
1&
1.
0%
0-
0$
0,
0#
0+
b11000 "
#250000
1#
1+
b11001 "
#260000
1$
1,
0#
0+
b11010 "
#270000
1#
1+
b11011 "
#280000
1%
1-
0$
0,
0#
0+
b11100 "
#290000
1#
1+
b11101 "
#300000
1$
1,
0#
0+
b11110 "
#310000
1#
1+
b11111 "
#320000
b101 3
b101 !
1(
10
0'
0/
0&
0.
0%
0-
0$
0,
0#
0+
b100000 "
#330000
1#
1+
b100001 "
#340000
1$
1,
0#
0+
b100010 "
#350000
1#
1+
b100011 "
#360000
1%
1-
0$
0,
0#
0+
b100100 "
#370000
1#
1+
b100101 "
#380000
1$
1,
0#
0+
b100110 "
#390000
1#
1+
b100111 "
#400000
1&
1.
0%
0-
0$
0,
0#
0+
b101000 "
#410000
1#
1+
b101001 "
#420000
1$
1,
0#
0+
b101010 "
#430000
1#
1+
b101011 "
#440000
1%
1-
0$
0,
0#
0+
b101100 "
#450000
1#
1+
b101101 "
#460000
1$
1,
0#
0+
b101110 "
#470000
1#
1+
b101111 "
#480000
1'
1/
0&
0.
0%
0-
0$
0,
0#
0+
b110000 "
#490000
1#
1+
b110001 "
#500000
1$
1,
0#
0+
b110010 "
#510000
1#
1+
b110011 "
#520000
1%
1-
0$
0,
0#
0+
b110100 "
#530000
1#
1+
b110101 "
#540000
1$
1,
0#
0+
b110110 "
#550000
1#
1+
b110111 "
#560000
1&
1.
0%
0-
0$
0,
0#
0+
b111000 "
#570000
1#
1+
b111001 "
#580000
1$
1,
0#
0+
b111010 "
#590000
1#
1+
b111011 "
#600000
1%
1-
0$
0,
0#
0+
b111100 "
#610000
1#
1+
b111101 "
#620000
1$
1,
0#
0+
b111110 "
#630000
1#
1+
b111111 "
#640000
b110 3
b110 !
1)
11
0(
00
0'
0/
0&
0.
0%
0-
0$
0,
0#
0+
b1000000 "
#650000
1#
1+
b1000001 "
#660000
1$
1,
0#
0+
b1000010 "
#670000
1#
1+
b1000011 "
#680000
1%
1-
0$
0,
0#
0+
b1000100 "
#690000
1#
1+
b1000101 "
#700000
1$
1,
0#
0+
b1000110 "
#710000
1#
1+
b1000111 "
#720000
1&
1.
0%
0-
0$
0,
0#
0+
b1001000 "
#730000
1#
1+
b1001001 "
#740000
1$
1,
0#
0+
b1001010 "
#750000
1#
1+
b1001011 "
#760000
1%
1-
0$
0,
0#
0+
b1001100 "
#770000
1#
1+
b1001101 "
#780000
1$
1,
0#
0+
b1001110 "
#790000
1#
1+
b1001111 "
#800000
1'
1/
0&
0.
0%
0-
0$
0,
0#
0+
b1010000 "
#810000
1#
1+
b1010001 "
#820000
1$
1,
0#
0+
b1010010 "
#830000
1#
1+
b1010011 "
#840000
1%
1-
0$
0,
0#
0+
b1010100 "
#850000
1#
1+
b1010101 "
#860000
1$
1,
0#
0+
b1010110 "
#870000
1#
1+
b1010111 "
#880000
1&
1.
0%
0-
0$
0,
0#
0+
b1011000 "
#890000
1#
1+
b1011001 "
#900000
1$
1,
0#
0+
b1011010 "
#910000
1#
1+
b1011011 "
#920000
1%
1-
0$
0,
0#
0+
b1011100 "
#930000
1#
1+
b1011101 "
#940000
1$
1,
0#
0+
b1011110 "
#950000
1#
1+
b1011111 "
#960000
1(
10
0'
0/
0&
0.
0%
0-
0$
0,
0#
0+
b1100000 "
#970000
1#
1+
b1100001 "
#980000
1$
1,
0#
0+
b1100010 "
#990000
1#
1+
b1100011 "
#1000000
1%
1-
0$
0,
0#
0+
b1100100 "
#1010000
1#
1+
b1100101 "
#1020000
1$
1,
0#
0+
b1100110 "
#1030000
1#
1+
b1100111 "
#1040000
1&
1.
0%
0-
0$
0,
0#
0+
b1101000 "
#1050000
1#
1+
b1101001 "
#1060000
1$
1,
0#
0+
b1101010 "
#1070000
1#
1+
b1101011 "
#1080000
1%
1-
0$
0,
0#
0+
b1101100 "
#1090000
1#
1+
b1101101 "
#1100000
1$
1,
0#
0+
b1101110 "
#1110000
1#
1+
b1101111 "
#1120000
1'
1/
0&
0.
0%
0-
0$
0,
0#
0+
b1110000 "
#1130000
1#
1+
b1110001 "
#1140000
1$
1,
0#
0+
b1110010 "
#1150000
1#
1+
b1110011 "
#1160000
1%
1-
0$
0,
0#
0+
b1110100 "
#1170000
1#
1+
b1110101 "
#1180000
1$
1,
0#
0+
b1110110 "
#1190000
1#
1+
b1110111 "
#1200000
1&
1.
0%
0-
0$
0,
0#
0+
b1111000 "
#1210000
1#
1+
b1111001 "
#1220000
1$
1,
0#
0+
b1111010 "
#1230000
1#
1+
b1111011 "
#1240000
1%
1-
0$
0,
0#
0+
b1111100 "
#1250000
1#
1+
b1111101 "
#1260000
1$
1,
0#
0+
b1111110 "
#1270000
1#
1+
b1111111 "
#1280000
b111 3
b111 !
1*
12
0)
01
0(
00
0'
0/
0&
0.
0%
0-
0$
0,
0#
0+
b10000000 "
#1290000
1#
1+
b10000001 "
#1300000
1$
1,
0#
0+
b10000010 "
#1310000
1#
1+
b10000011 "
#1320000
1%
1-
0$
0,
0#
0+
b10000100 "
#1330000
1#
1+
b10000101 "
#1340000
1$
1,
0#
0+
b10000110 "
#1350000
1#
1+
b10000111 "
#1360000
1&
1.
0%
0-
0$
0,
0#
0+
b10001000 "
#1370000
1#
1+
b10001001 "
#1380000
1$
1,
0#
0+
b10001010 "
#1390000
1#
1+
b10001011 "
#1400000
1%
1-
0$
0,
0#
0+
b10001100 "
#1410000
1#
1+
b10001101 "
#1420000
1$
1,
0#
0+
b10001110 "
#1430000
1#
1+
b10001111 "
#1440000
1'
1/
0&
0.
0%
0-
0$
0,
0#
0+
b10010000 "
#1450000
1#
1+
b10010001 "
#1460000
1$
1,
0#
0+
b10010010 "
#1470000
1#
1+
b10010011 "
#1480000
1%
1-
0$
0,
0#
0+
b10010100 "
#1490000
1#
1+
b10010101 "
#1500000
1$
1,
0#
0+
b10010110 "
#1510000
1#
1+
b10010111 "
#1520000
1&
1.
0%
0-
0$
0,
0#
0+
b10011000 "
#1530000
1#
1+
b10011001 "
#1540000
1$
1,
0#
0+
b10011010 "
#1550000
1#
1+
b10011011 "
#1560000
1%
1-
0$
0,
0#
0+
b10011100 "
#1570000
1#
1+
b10011101 "
#1580000
1$
1,
0#
0+
b10011110 "
#1590000
1#
1+
b10011111 "
#1600000
1(
10
0'
0/
0&
0.
0%
0-
0$
0,
0#
0+
b10100000 "
#1610000
1#
1+
b10100001 "
#1620000
1$
1,
0#
0+
b10100010 "
#1630000
1#
1+
b10100011 "
#1640000
1%
1-
0$
0,
0#
0+
b10100100 "
#1650000
1#
1+
b10100101 "
#1660000
1$
1,
0#
0+
b10100110 "
#1670000
1#
1+
b10100111 "
#1680000
1&
1.
0%
0-
0$
0,
0#
0+
b10101000 "
#1690000
1#
1+
b10101001 "
#1700000
1$
1,
0#
0+
b10101010 "
#1710000
1#
1+
b10101011 "
#1720000
1%
1-
0$
0,
0#
0+
b10101100 "
#1730000
1#
1+
b10101101 "
#1740000
1$
1,
0#
0+
b10101110 "
#1750000
1#
1+
b10101111 "
#1760000
1'
1/
0&
0.
0%
0-
0$
0,
0#
0+
b10110000 "
#1770000
1#
1+
b10110001 "
#1780000
1$
1,
0#
0+
b10110010 "
#1790000
1#
1+
b10110011 "
#1800000
1%
1-
0$
0,
0#
0+
b10110100 "
#1810000
1#
1+
b10110101 "
#1820000
1$
1,
0#
0+
b10110110 "
#1830000
1#
1+
b10110111 "
#1840000
1&
1.
0%
0-
0$
0,
0#
0+
b10111000 "
#1850000
1#
1+
b10111001 "
#1860000
1$
1,
0#
0+
b10111010 "
#1870000
1#
1+
b10111011 "
#1880000
1%
1-
0$
0,
0#
0+
b10111100 "
#1890000
1#
1+
b10111101 "
#1900000
1$
1,
0#
0+
b10111110 "
#1910000
1#
1+
b10111111 "
#1920000
1)
11
0(
00
0'
0/
0&
0.
0%
0-
0$
0,
0#
0+
b11000000 "
#1930000
1#
1+
b11000001 "
#1940000
1$
1,
0#
0+
b11000010 "
#1950000
1#
1+
b11000011 "
#1960000
1%
1-
0$
0,
0#
0+
b11000100 "
#1970000
1#
1+
b11000101 "
#1980000
1$
1,
0#
0+
b11000110 "
#1990000
1#
1+
b11000111 "
#2000000
1&
1.
0%
0-
0$
0,
0#
0+
b11001000 "
#2010000
1#
1+
b11001001 "
#2020000
1$
1,
0#
0+
b11001010 "
#2030000
1#
1+
b11001011 "
#2040000
1%
1-
0$
0,
0#
0+
b11001100 "
#2050000
1#
1+
b11001101 "
#2060000
1$
1,
0#
0+
b11001110 "
#2070000
1#
1+
b11001111 "
#2080000
1'
1/
0&
0.
0%
0-
0$
0,
0#
0+
b11010000 "
#2090000
1#
1+
b11010001 "
#2100000
1$
1,
0#
0+
b11010010 "
#2110000
1#
1+
b11010011 "
#2120000
1%
1-
0$
0,
0#
0+
b11010100 "
#2130000
1#
1+
b11010101 "
#2140000
1$
1,
0#
0+
b11010110 "
#2150000
1#
1+
b11010111 "
#2160000
1&
1.
0%
0-
0$
0,
0#
0+
b11011000 "
#2170000
1#
1+
b11011001 "
#2180000
1$
1,
0#
0+
b11011010 "
#2190000
1#
1+
b11011011 "
#2200000
1%
1-
0$
0,
0#
0+
b11011100 "
#2210000
1#
1+
b11011101 "
#2220000
1$
1,
0#
0+
b11011110 "
#2230000
1#
1+
b11011111 "
#2240000
1(
10
0'
0/
0&
0.
0%
0-
0$
0,
0#
0+
b11100000 "
#2250000
1#
1+
b11100001 "
#2260000
1$
1,
0#
0+
b11100010 "
#2270000
1#
1+
b11100011 "
#2280000
1%
1-
0$
0,
0#
0+
b11100100 "
#2290000
1#
1+
b11100101 "
#2300000
1$
1,
0#
0+
b11100110 "
#2310000
1#
1+
b11100111 "
#2320000
1&
1.
0%
0-
0$
0,
0#
0+
b11101000 "
#2330000
1#
1+
b11101001 "
#2340000
1$
1,
0#
0+
b11101010 "
#2350000
1#
1+
b11101011 "
#2360000
1%
1-
0$
0,
0#
0+
b11101100 "
#2370000
1#
1+
b11101101 "
#2380000
1$
1,
0#
0+
b11101110 "
#2390000
1#
1+
b11101111 "
#2400000
1'
1/
0&
0.
0%
0-
0$
0,
0#
0+
b11110000 "
#2410000
1#
1+
b11110001 "
#2420000
1$
1,
0#
0+
b11110010 "
#2430000
1#
1+
b11110011 "
#2440000
1%
1-
0$
0,
0#
0+
b11110100 "
#2450000
1#
1+
b11110101 "
#2460000
1$
1,
0#
0+
b11110110 "
#2470000
1#
1+
b11110111 "
#2480000
1&
1.
0%
0-
0$
0,
0#
0+
b11111000 "
#2490000
1#
1+
b11111001 "
#2500000
1$
1,
0#
0+
b11111010 "
#2510000
1#
1+
b11111011 "
#2520000
1%
1-
0$
0,
0#
0+
b11111100 "
#2530000
1#
1+
b11111101 "
#2540000
1$
1,
0#
0+
b11111110 "
#2550000
1#
1+
b11111111 "
#2560000
b100000000 "
