Intermediate_Projects/02_Ripple_Carry_Adder_4_Bit/Ripple_Carry_Adder_4_Bit_behavioural.v
module Ripple_Carry_Adder_4_Bit_behavioural(input [3:0] a,input [3:0] b,input cin, output reg [3:0] s,output reg cout);

reg [4:0] temp;

always @(*) begin
    temp=a+b+cin;
    s=temp[3:0];
    cout=temp[4];
end
 endmodule

Intermediate_Projects/02_Ripple_Carry_Adder_4_Bit/testbench.v
`timescale 1ns/1ns

module testbench;
reg [3:0] a;
reg [3:0] b;
reg cin;
wire [3:0] s;
wire cout;


Ripple_Carry_Adder_4_Bit_behavioural behav(.a(a),.b(b),.cin(cin),.s(s),.cout(cout));

integer i;
initial begin

$dumpfile("Ripple_Carry_Adder_4_Bit.vcd");
$dumpvars(0,testbench);


for(i=0;i<512;i=i+1)
begin
{a,b,cin}=i[8:0];//here 256 cases becoz a will have 4 bits and b also and 1bit of cin so total 9 so2^9=512
#10;
$display("| a = %b | b = %b | cin = %b | sum = %b | cout = %b |", a, b, cin, s, cout);

end




end


endmodule

Intermediate_Projects/02_Ripple_Carry_Adder_4_Bit/Ripple_Carry_Adder_4_Bit.vcd
$date
	Wed Jun 18 10:19:23 2025
$end
$version
	Icarus Verilog
$end
$timescale
	1s
$end
$scope module testbench $end
$var wire 1 ! cout $end
$var wire 4 " s [3:0] $end
$var reg 4 # a [3:0] $end
$var reg 4 $ b [3:0] $end
$var reg 1 % cin $end
$var integer 32 & i [31:0] $end
$scope module behav $end
$var wire 4 ' a [3:0] $end
$var wire 4 ( b [3:0] $end
$var wire 1 ) cin $end
$var reg 1 * cout $end
$var reg 4 + s [3:0] $end
$var reg 5 , temp [4:0] $end
$upscope $end
$upscope $end
$enddefinitions $end
#0
$dumpvars
b0 ,
b0 +
0*
0)
b0 (
b0 '
b0 &
0%
b0 $
b0 #
b0 "
0!
$end
#10
b1 +
b1 "
b1 ,
1%
1)
b1 &
#20
b1 $
b1 (
0%
0)
b10 &
#30
b10 +
b10 "
b10 ,
1%
1)
b11 &
#40
b10 $
b10 (
0%
0)
b100 &
#50
b11 +
b11 "
b11 ,
1%
1)
b101 &
#60
b11 $
b11 (
0%
0)
b110 &
#70
b100 +
b100 "
b100 ,
1%
1)
b111 &
#80
b100 $
b100 (
0%
0)
b1000 &
#90
b101 +
b101 "
b101 ,
1%
1)
b1001 &
#100
b101 $
b101 (
0%
0)
b1010 &
#110
b110 +
b110 "
b110 ,
1%
1)
b1011 &
#120
b110 $
b110 (
0%
0)
b1100 &
#130
b111 +
b111 "
b111 ,
1%
1)
b1101 &
#140
b111 $
b111 (
0%
0)
b1110 &
#150
b1000 +
b1000 "
b1000 ,
1%
1)
b1111 &
#160
b1000 $
b1000 (
0%
0)
b10000 &
#170
b1001 +
b1001 "
b1001 ,
1%
1)
b10001 &
#180
b1001 $
b1001 (
0%
0)
b10010 &
#190
b1010 +
b1010 "
b1010 ,
1%
1)
b10011 &
#200
b1010 $
b1010 (
0%
0)
b10100 &
#210
b1011 +
b1011 "
b1011 ,
1%
1)
b10101 &
#220
b1011 $
b1011 (
0%
0)
b10110 &
#230
b1100 +
b1100 "
b1100 ,
1%
1)
b10111 &
#240
b1100 $
b1100 (
0%
0)
b11000 &
#250
b1101 +
b1101 "
b1101 ,
1%
1)
b11001 &
#260
b1101 $
b1101 (
0%
0)
b11010 &
#270
b1110 +
b1110 "
b1110 ,
1%
1)
b11011 &
#280
b1110 $
b1110 (
0%
0)
b11100 &
#290
b1111 +
b1111 "
b1111 ,
1%
1)
b11101 &
#300
b1111 $
b1111 (
0%
0)
b11110 &
#310
1*
1!
b0 +
b0 "
b10000 ,
1%
1)
b11111 &
#320
0*
0!
b1 +
b1 "
b1 ,
b1 #
b1 '
b0 $
b0 (
0%
0)
b100000 &
#330
b10 +
b10 "
b10 ,
1%
1)
b100001 &
#340
b1 $
b1 (
0%
0)
b100010 &
#350
b11 +
b11 "
b11 ,
1%
1)
b100011 &
#360
b10 $
b10 (
0%
0)
b100100 &
#370
b100 +
b100 "
b100 ,
1%
1)
b100101 &
#380
b11 $
b11 (
0%
0)
b100110 &
#390
b101 +
b101 "
b101 ,
1%
1)
b100111 &
#400
b100 $
b100 (
0%
0)
b101000 &
#410
b110 +
b110 "
b110 ,
1%
1)
b101001 &
#420
b101 $
b101 (
0%
0)
b101010 &
#430
b111 +
b111 "
b111 ,
1%
1)
b101011 &
#440
b110 $
b110 (
0%
0)
b101100 &
#450
b1000 +
b1000 "
b1000 ,
1%
1)
b101101 &
#460
b111 $
b111 (
0%
0)
b101110 &
#470
b1001 +
b1001 "
b1001 ,
1%
1)
b101111 &
#480
b1000 $
b1000 (
0%
0)
b110000 &
#490
b1010 +
b1010 "
b1010 ,
1%
1)
b110001 &
#500
b1001 $
b1001 (
0%
0)
b110010 &
#510
b1011 +
b1011 "
b1011 ,
1%
1)
b110011 &
#520
b1010 $
b1010 (
0%
0)
b110100 &
#530
b1100 +
b1100 "
b1100 ,
1%
1)
b110101 &
#540
b1011 $
b1011 (
0%
0)
b110110 &
#550
b1101 +
b1101 "
b1101 ,
1%
1)
b110111 &
#560
b1100 $
b1100 (
0%
0)
b111000 &
#570
b1110 +
b1110 "
b1110 ,
1%
1)
b111001 &
#580
b1101 $
b1101 (
0%
0)
b111010 &
#590
b1111 +
b1111 "
b1111 ,
1%
1)
b111011 &
#600
b1110 $
b1110 (
0%
0)
b111100 &
#610
1*
1!
b0 +
b0 "
b10000 ,
1%
1)
b111101 &
#620
b1111 $
b1111 (
0%
0)
b111110 &
#630
b1 +
b1 "
b10001 ,
1%
1)
b111111 &
#640
0*
0!
b10 +
b10 "
b10 ,
b10 #
b10 '
b0 $
b0 (
0%
0)
b1000000 &
#650
b11 +
b11 "
b11 ,
1%
1)
b1000001 &
#660
b1 $
b1 (
0%
0)
b1000010 &
#670
b100 +
b100 "
b100 ,
1%
1)
b1000011 &
#680
b10 $
b10 (
0%
0)
b1000100 &
#690
b101 +
b101 "
b101 ,
1%
1)
b1000101 &
#700
b11 $
b11 (
0%
0)
b1000110 &
#710
b110 +
b110 "
b110 ,
1%
1)
b1000111 &
#720
b100 $
b100 (
0%
0)
b1001000 &
#730
b111 +
b111 "
b111 ,
1%
1)
b1001001 &
#740
b101 $
b101 (
0%
0)
b1001010 &
#750
b1000 +
b1000 "
b1000 ,
1%
1)
b1001011 &
#760
b110 $
b110 (
0%
0)
b1001100 &
#770
b1001 +
b1001 "
b1001 ,
1%
1)
b1001101 &
#780
b111 $
b111 (
0%
0)
b1001110 &
#790
b1010 +
b1010 "
b1010 ,
1%
1)
b1001111 &
#800
b1000 $
b1000 (
0%
0)
b1010000 &
#810
b1011 +
b1011 "
b1011 ,
1%
1)
b1010001 &
#820
b1001 $
b1001 (
0%
0)
b1010010 &
#830
b1100 +
b1100 "
b1100 ,
1%
1)
b1010011 &
#840
b1010 $
b1010 (
0%
0)
b1010100 &
#850
b1101 +
b1101 "
b1101 ,
1%
1)
b1010101 &
#860
b1011 $
b1011 (
0%
0)
b1010110 &
#870
b1110 +
b1110 "
b1110 ,
1%
1)
b1010111 &
#880
b1100 $
b1100 (
0%
0)
b1011000 &
#890
b1111 +
b1111 "
b1111 ,
1%
1)
b1011001 &
#900
b1101 $
b1101 (
0%
0)
b1011010 &
#910
1*
1!
b0 +
b0 "
b10000 ,
1%
1)
b1011011 &
#920
b1110 $
b1110 (
0%
0)
b1011100 &
#930
b1 +
b1 "
b10001 ,
1%
1)
b1011101 &
#940
b1111 $
b1111 (
0%
0)
b1011110 &
#950
b10 +
b10 "
b10010 ,
1%
1)
b1011111 &
#960
0*
0!
b11 +
b11 "
b11 ,
b11 #
b11 '
b0 $
b0 (
0%
0)
b1100000 &
#970
b100 +
b100 "
b100 ,
1%
1)
b1100001 &
#980
b1 $
b1 (
0%
0)
b1100010 &
#990
b101 +
b101 "
b101 ,
1%
1)
b1100011 &
#1000
b10 $
b10 (
0%
0)
b1100100 &
#1010
b110 +
b110 "
b110 ,
1%
1)
b1100101 &
#1020
b11 $
b11 (
0%
0)
b1100110 &
#1030
b111 +
b111 "
b111 ,
1%
1)
b1100111 &
#1040
b100 $
b100 (
0%
0)
b1101000 &
#1050
b1000 +
b1000 "
b1000 ,
1%
1)
b1101001 &
#1060
b101 $
b101 (
0%
0)
b1101010 &
#1070
b1001 +
b1001 "
b1001 ,
1%
1)
b1101011 &
#1080
b110 $
b110 (
0%
0)
b1101100 &
#1090
b1010 +
b1010 "
b1010 ,
1%
1)
b1101101 &
#1100
b111 $
b111 (
0%
0)
b1101110 &
#1110
b1011 +
b1011 "
b1011 ,
1%
1)
b1101111 &
#1120
b1000 $
b1000 (
0%
0)
b1110000 &
#1130
b1100 +
b1100 "
b1100 ,
1%
1)
b1110001 &
#1140
b1001 $
b1001 (
0%
0)
b1110010 &
#1150
b1101 +
b1101 "
b1101 ,
1%
1)
b1110011 &
#1160
b1010 $
b1010 (
0%
0)
b1110100 &
#1170
b1110 +
b1110 "
b1110 ,
1%
1)
b1110101 &
#1180
b1011 $
b1011 (
0%
0)
b1110110 &
#1190
b1111 +
b1111 "
b1111 ,
1%
1)
b1110111 &
#1200
b1100 $
b1100 (
0%
0)
b1111000 &
#1210
1*
1!
b0 +
b0 "
b10000 ,
1%
1)
b1111001 &
#1220
b1101 $
b1101 (
0%
0)
b1111010 &
#1230
b1 +
b1 "
b10001 ,
1%
1)
b1111011 &
#1240
b1110 $
b1110 (
0%
0)
b1111100 &
#1250
b10 +
b10 "
b10010 ,
1%
1)
b1111101 &
#1260
b1111 $
b1111 (
0%
0)
b1111110 &
#1270
b11 +
b11 "
b10011 ,
1%
1)
b1111111 &
#1280
0*
0!
b100 +
b100 "
b100 ,
b100 #
b100 '
b0 $
b0 (
0%
0)
b10000000 &
#1290
b101 +
b101 "
b101 ,
1%
1)
b10000001 &
#1300
b1 $
b1 (
0%
0)
b10000010 &
#1310
b110 +
b110 "
b110 ,
1%
1)
b10000011 &
#1320
b10 $
b10 (
0%
0)
b10000100 &
#1330
b111 +
b111 "
b111 ,
1%
1)
b10000101 &
#1340
b11 $
b11 (
0%
0)
b10000110 &
#1350
b1000 +
b1000 "
b1000 ,
1%
1)
b10000111 &
#1360
b100 $
b100 (
0%
0)
b10001000 &
#1370
b1001 +
b1001 "
b1001 ,
1%
1)
b10001001 &
#1380
b101 $
b101 (
0%
0)
b10001010 &
#1390
b1010 +
b1010 "
b1010 ,
1%
1)
b10001011 &
#1400
b110 $
b110 (
0%
0)
b10001100 &
#1410
b1011 +
b1011 "
b1011 ,
1%
1)
b10001101 &
#1420
b111 $
b111 (
0%
0)
b10001110 &
#1430
b1100 +
b1100 "
b1100 ,
1%
1)
b10001111 &
#1440
b1000 $
b1000 (
0%
0)
b10010000 &
#1450
b1101 +
b1101 "
b1101 ,
1%
1)
b10010001 &
#1460
b1001 $
b1001 (
0%
0)
b10010010 &
#1470
b1110 +
b1110 "
b1110 ,
1%
1)
b10010011 &
#1480
b1010 $
b1010 (
0%
0)
b10010100 &
#1490
b1111 +
b1111 "
b1111 ,
1%
1)
b10010101 &
#1500
b1011 $
b1011 (
0%
0)
b10010110 &
#1510
1*
1!
b0 +
b0 "
b10000 ,
1%
1)
b10010111 &
#1520
b1100 $
b1100 (
0%
0)
b10011000 &
#1530
b1 +
b1 "
b10001 ,
1%
1)
b10011001 &
#1540
b1101 $
b1101 (
0%
0)
b10011010 &
#1550
b10 +
b10 "
b10010 ,
1%
1)
b10011011 &
#1560
b1110 $
b1110 (
0%
0)
b10011100 &
#1570
b11 +
b11 "
b10011 ,
1%
1)
b10011101 &
#1580
b1111 $
b1111 (
0%
0)
b10011110 &
#1590
b100 +
b100 "
b10100 ,
1%
1)
b10011111 &
#1600
0*
0!
b101 +
b101 "
b101 ,
b101 #
b101 '
b0 $
b0 (
0%
0)
b10100000 &
#1610
b110 +
b110 "
b110 ,
1%
1)
b10100001 &
#1620
b1 $
b1 (
0%
0)
b10100010 &
#1630
b111 +
b111 "
b111 ,
1%
1)
b10100011 &
#1640
b10 $
b10 (
0%
0)
b10100100 &
#1650
b1000 +
b1000 "
b1000 ,
1%
1)
b10100101 &
#1660
b11 $
b11 (
0%
0)
b10100110 &
#1670
b1001 +
b1001 "
b1001 ,
1%
1)
b10100111 &
#1680
b100 $
b100 (
0%
0)
b10101000 &
#1690
b1010 +
b1010 "
b1010 ,
1%
1)
b10101001 &
#1700
b101 $
b101 (
0%
0)
b10101010 &
#1710
b1011 +
b1011 "
b1011 ,
1%
1)
b10101011 &
#1720
b110 $
b110 (
0%
0)
b10101100 &
#1730
b1100 +
b1100 "
b1100 ,
1%
1)
b10101101 &
#1740
b111 $
b111 (
0%
0)
b10101110 &
#1750
b1101 +
b1101 "
b1101 ,
1%
1)
b10101111 &
#1760
b1000 $
b1000 (
0%
0)
b10110000 &
#1770
b1110 +
b1110 "
b1110 ,
1%
1)
b10110001 &
#1780
b1001 $
b1001 (
0%
0)
b10110010 &
#1790
b1111 +
b1111 "
b1111 ,
1%
1)
b10110011 &
#1800
b1010 $
b1010 (
0%
0)
b10110100 &
#1810
1*
1!
b0 +
b0 "
b10000 ,
1%
1)
b10110101 &
#1820
b1011 $
b1011 (
0%
0)
b10110110 &
#1830
b1 +
b1 "
b10001 ,
1%
1)
b10110111 &
#1840
b1100 $
b1100 (
0%
0)
b10111000 &
#1850
b10 +
b10 "
b10010 ,
1%
1)
b10111001 &
#1860
b1101 $
b1101 (
0%
0)
b10111010 &
#1870
b11 +
b11 "
b10011 ,
1%
1)
b10111011 &
#1880
b1110 $
b1110 (
0%
0)
b10111100 &
#1890
b100 +
b100 "
b10100 ,
1%
1)
b10111101 &
#1900
b1111 $
b1111 (
0%
0)
b10111110 &
#1910
b101 +
b101 "
b10101 ,
1%
1)
b10111111 &
#1920
0*
0!
b110 +
b110 "
b110 ,
b110 #
b110 '
b0 $
b0 (
0%
0)
b11000000 &
#1930
b111 +
b111 "
b111 ,
1%
1)
b11000001 &
#1940
b1 $
b1 (
0%
0)
b11000010 &
#1950
b1000 +
b1000 "
b1000 ,
1%
1)
b11000011 &
#1960
b10 $
b10 (
0%
0)
b11000100 &
#1970
b1001 +
b1001 "
b1001 ,
1%
1)
b11000101 &
#1980
b11 $
b11 (
0%
0)
b11000110 &
#1990
b1010 +
b1010 "
b1010 ,
1%
1)
b11000111 &
#2000
b100 $
b100 (
0%
0)
b11001000 &
#2010
b1011 +
b1011 "
b1011 ,
1%
1)
b11001001 &
#2020
b101 $
b101 (
0%
0)
b11001010 &
#2030
b1100 +
b1100 "
b1100 ,
1%
1)
b11001011 &
#2040
b110 $
b110 (
0%
0)
b11001100 &
#2050
b1101 +
b1101 "
b1101 ,
1%
1)
b11001101 &
#2060
b111 $
b111 (
0%
0)
b11001110 &
#2070
b1110 +
b1110 "
b1110 ,
1%
1)
b11001111 &
#2080
b1000 $
b1000 (
0%
0)
b11010000 &
#2090
b1111 +
b1111 "
b1111 ,
1%
1)
b11010001 &
#2100
b1001 $
b1001 (
0%
0)
b11010010 &
#2110
1*
1!
b0 +
b0 "
b10000 ,
1%
1)
b11010011 &
#2120
b1010 $
b1010 (
0%
0)
b11010100 &
#2130
b1 +
b1 "
b10001 ,
1%
1)
b11010101 &
#2140
b1011 $
b1011 (
0%
0)
b11010110 &
#2150
b10 +
b10 "
b10010 ,
1%
1)
b11010111 &
#2160
b1100 $
b1100 (
0%
0)
b11011000 &
#2170
b11 +
b11 "
b10011 ,
1%
1)
b11011001 &
#2180
b1101 $
b1101 (
0%
0)
b11011010 &
#2190
b100 +
b100 "
b10100 ,
1%
1)
b11011011 &
#2200
b1110 $
b1110 (
0%
0)
b11011100 &
#2210
b101 +
b101 "
b10101 ,
1%
1)
b11011101 &
#2220
b1111 $
b1111 (
0%
0)
b11011110 &
#2230
b110 +
b110 "
b10110 ,
1%
1)
b11011111 &
#2240
0*
0!
b111 +
b111 "
b111 ,
b111 #
b111 '
b0 $
b0 (
0%
0)
b11100000 &
#2250
b1000 +
b1000 "
b1000 ,
1%
1)
b11100001 &
#2260
b1 $
b1 (
0%
0)
b11100010 &
#2270
b1001 +
b1001 "
b1001 ,
1%
1)
b11100011 &
#2280
b10 $
b10 (
0%
0)
b11100100 &
#2290
b1010 +
b1010 "
b1010 ,
1%
1)
b11100101 &
#2300
b11 $
b11 (
0%
0)
b11100110 &
#2310
b1011 +
b1011 "
b1011 ,
1%
1)
b11100111 &
#2320
b100 $
b100 (
0%
0)
b11101000 &
#2330
b1100 +
b1100 "
b1100 ,
1%
1)
b11101001 &
#2340
b101 $
b101 (
0%
0)
b11101010 &
#2350
b1101 +
b1101 "
b1101 ,
1%
1)
b11101011 &
#2360
b110 $
b110 (
0%
0)
b11101100 &
#2370
b1110 +
b1110 "
b1110 ,
1%
1)
b11101101 &
#2380
b111 $
b111 (
0%
0)
b11101110 &
#2390
b1111 +
b1111 "
b1111 ,
1%
1)
b11101111 &
#2400
b1000 $
b1000 (
0%
0)
b11110000 &
#2410
1*
1!
b0 +
b0 "
b10000 ,
1%
1)
b11110001 &
#2420
b1001 $
b1001 (
0%
0)
b11110010 &
#2430
b1 +
b1 "
b10001 ,
1%
1)
b11110011 &
#2440
b1010 $
b1010 (
0%
0)
b11110100 &
#2450
b10 +
b10 "
b10010 ,
1%
1)
b11110101 &
#2460
b1011 $
b1011 (
0%
0)
b11110110 &
#2470
b11 +
b11 "
b10011 ,
1%
1)
b11110111 &
#2480
b1100 $
b1100 (
0%
0)
b11111000 &
#2490
b100 +
b100 "
b10100 ,
1%
1)
b11111001 &
#2500
b1101 $
b1101 (
0%
0)
b11111010 &
#2510
b101 +
b101 "
b10101 ,
1%
1)
b11111011 &
#2520
b1110 $
b1110 (
0%
0)
b11111100 &
#2530
b110 +
b110 "
b10110 ,
1%
1)
b11111101 &
#2540
b1111 $
b1111 (
0%
0)
b11111110 &
#2550
b111 +
b111 "
b10111 ,
1%
1)
b11111111 &
#2560
0*
0!
b1000 +
b1000 "
b1000 ,
b1000 #
b1000 '
b0 $
b0 (
0%
0)
b100000000 &
#2570
b1001 +
b1001 "
b1001 ,
1%
1)
b100000001 &
#2580
b1 $
b1 (
0%
0)
b100000010 &
#2590
b1010 +
b1010 "
b1010 ,
1%
1)
b100000011 &
#2600
b10 $
b10 (
0%
0)
b100000100 &
#2610
b1011 +
b1011 "
b1011 ,
1%
1)
b100000101 &
#2620
b11 $
b11 (
0%
0)
b100000110 &
#2630
b1100 +
b1100 "
b1100 ,
1%
1)
b100000111 &
#2640
b100 $
b100 (
0%
0)
b100001000 &
#2650
b1101 +
b1101 "
b1101 ,
1%
1)
b100001001 &
#2660
b101 $
b101 (
0%
0)
b100001010 &
#2670
b1110 +
b1110 "
b1110 ,
1%
1)
b100001011 &
#2680
b110 $
b110 (
0%
0)
b100001100 &
#2690
b1111 +
b1111 "
b1111 ,
1%
1)
b100001101 &
#2700
b111 $
b111 (
0%
0)
b100001110 &
#2710
1*
1!
b0 +
b0 "
b10000 ,
1%
1)
b100001111 &
#2720
b1000 $
b1000 (
0%
0)
b100010000 &
#2730
b1 +
b1 "
b10001 ,
1%
1)
b100010001 &
#2740
b1001 $
b1001 (
0%
0)
b100010010 &
#2750
b10 +
b10 "
b10010 ,
1%
1)
b100010011 &
#2760
b1010 $
b1010 (
0%
0)
b100010100 &
#2770
b11 +
b11 "
b10011 ,
1%
1)
b100010101 &
#2780
b1011 $
b1011 (
0%
0)
b100010110 &
#2790
b100 +
b100 "
b10100 ,
1%
1)
b100010111 &
#2800
b1100 $
b1100 (
0%
0)
b100011000 &
#2810
b101 +
b101 "
b10101 ,
1%
1)
b100011001 &
#2820
b1101 $
b1101 (
0%
0)
b100011010 &
#2830
b110 +
b110 "
b10110 ,
1%
1)
b100011011 &
#2840
b1110 $
b1110 (
0%
0)
b100011100 &
#2850
b111 +
b111 "
b10111 ,
1%
1)
b100011101 &
#2860
b1111 $
b1111 (
0%
0)
b100011110 &
#2870
b1000 +
b1000 "
b11000 ,
1%
1)
b100011111 &
#2880
0*
0!
b1001 +
b1001 "
b1001 ,
b1001 #
b1001 '
b0 $
b0 (
0%
0)
b100100000 &
#2890
b1010 +
b1010 "
b1010 ,
1%
1)
b100100001 &
#2900
b1 $
b1 (
0%
0)
b100100010 &
#2910
b1011 +
b1011 "
b1011 ,
1%
1)
b100100011 &
#2920
b10 $
b10 (
0%
0)
b100100100 &
#2930
b1100 +
b1100 "
b1100 ,
1%
1)
b100100101 &
#2940
b11 $
b11 (
0%
0)
b100100110 &
#2950
b1101 +
b1101 "
b1101 ,
1%
1)
b100100111 &
#2960
b100 $
b100 (
0%
0)
b100101000 &
#2970
b1110 +
b1110 "
b1110 ,
1%
1)
b100101001 &
#2980
b101 $
b101 (
0%
0)
b100101010 &
#2990
b1111 +
b1111 "
b1111 ,
1%
1)
b100101011 &
#3000
b110 $
b110 (
0%
0)
b100101100 &
#3010
1*
1!
b0 +
b0 "
b10000 ,
1%
1)
b100101101 &
#3020
b111 $
b111 (
0%
0)
b100101110 &
#3030
b1 +
b1 "
b10001 ,
1%
1)
b100101111 &
#3040
b1000 $
b1000 (
0%
0)
b100110000 &
#3050
b10 +
b10 "
b10010 ,
1%
1)
b100110001 &
#3060
b1001 $
b1001 (
0%
0)
b100110010 &
#3070
b11 +
b11 "
b10011 ,
1%
1)
b100110011 &
#3080
b1010 $
b1010 (
0%
0)
b100110100 &
#3090
b100 +
b100 "
b10100 ,
1%
1)
b100110101 &
#3100
b1011 $
b1011 (
0%
0)
b100110110 &
#3110
b101 +
b101 "
b10101 ,
1%
1)
b100110111 &
#3120
b1100 $
b1100 (
0%
0)
b100111000 &
#3130
b110 +
b110 "
b10110 ,
1%
1)
b100111001 &
#3140
b1101 $
b1101 (
0%
0)
b100111010 &
#3150
b111 +
b111 "
b10111 ,
1%
1)
b100111011 &
#3160
b1110 $
b1110 (
0%
0)
b100111100 &
#3170
b1000 +
b1000 "
b11000 ,
1%
1)
b100111101 &
#3180
b1111 $
b1111 (
0%
0)
b100111110 &
#3190
b1001 +
b1001 "
b11001 ,
1%
1)
b100111111 &
#3200
0*
0!
b1010 +
b1010 "
b1010 ,
b1010 #
b1010 '
b0 $
b0 (
0%
0)
b101000000 &
#3210
b1011 +
b1011 "
b1011 ,
1%
1)
b101000001 &
#3220
b1 $
b1 (
0%
0)
b101000010 &
#3230
b1100 +
b1100 "
b1100 ,
1%
1)
b101000011 &
#3240
b10 $
b10 (
0%
0)
b101000100 &
#3250
b1101 +
b1101 "
b1101 ,
1%
1)
b101000101 &
#3260
b11 $
b11 (
0%
0)
b101000110 &
#3270
b1110 +
b1110 "
b1110 ,
1%
1)
b101000111 &
#3280
b100 $
b100 (
0%
0)
b101001000 &
#3290
b1111 +
b1111 "
b1111 ,
1%
1)
b101001001 &
#3300
b101 $
b101 (
0%
0)
b101001010 &
#3310
1*
1!
b0 +
b0 "
b10000 ,
1%
1)
b101001011 &
#3320
b110 $
b110 (
0%
0)
b101001100 &
#3330
b1 +
b1 "
b10001 ,
1%
1)
b101001101 &
#3340
b111 $
b111 (
0%
0)
b101001110 &
#3350
b10 +
b10 "
b10010 ,
1%
1)
b101001111 &
#3360
b1000 $
b1000 (
0%
0)
b101010000 &
#3370
b11 +
b11 "
b10011 ,
1%
1)
b101010001 &
#3380
b1001 $
b1001 (
0%
0)
b101010010 &
#3390
b100 +
b100 "
b10100 ,
1%
1)
b101010011 &
#3400
b1010 $
b1010 (
0%
0)
b101010100 &
#3410
b101 +
b101 "
b10101 ,
1%
1)
b101010101 &
#3420
b1011 $
b1011 (
0%
0)
b101010110 &
#3430
b110 +
b110 "
b10110 ,
1%
1)
b101010111 &
#3440
b1100 $
b1100 (
0%
0)
b101011000 &
#3450
b111 +
b111 "
b10111 ,
1%
1)
b101011001 &
#3460
b1101 $
b1101 (
0%
0)
b101011010 &
#3470
b1000 +
b1000 "
b11000 ,
1%
1)
b101011011 &
#3480
b1110 $
b1110 (
0%
0)
b101011100 &
#3490
b1001 +
b1001 "
b11001 ,
1%
1)
b101011101 &
#3500
b1111 $
b1111 (
0%
0)
b101011110 &
#3510
b1010 +
b1010 "
b11010 ,
1%
1)
b101011111 &
#3520
0*
0!
b1011 +
b1011 "
b1011 ,
b1011 #
b1011 '
b0 $
b0 (
0%
0)
b101100000 &
#3530
b1100 +
b1100 "
b1100 ,
1%
1)
b101100001 &
#3540
b1 $
b1 (
0%
0)
b101100010 &
#3550
b1101 +
b1101 "
b1101 ,
1%
1)
b101100011 &
#3560
b10 $
b10 (
0%
0)
b101100100 &
#3570
b1110 +
b1110 "
b1110 ,
1%
1)
b101100101 &
#3580
b11 $
b11 (
0%
0)
b101100110 &
#3590
b1111 +
b1111 "
b1111 ,
1%
1)
b101100111 &
#3600
b100 $
b100 (
0%
0)
b101101000 &
#3610
1*
1!
b0 +
b0 "
b10000 ,
1%
1)
b101101001 &
#3620
b101 $
b101 (
0%
0)
b101101010 &
#3630
b1 +
b1 "
b10001 ,
1%
1)
b101101011 &
#3640
b110 $
b110 (
0%
0)
b101101100 &
#3650
b10 +
b10 "
b10010 ,
1%
1)
b101101101 &
#3660
b111 $
b111 (
0%
0)
b101101110 &
#3670
b11 +
b11 "
b10011 ,
1%
1)
b101101111 &
#3680
b1000 $
b1000 (
0%
0)
b101110000 &
#3690
b100 +
b100 "
b10100 ,
1%
1)
b101110001 &
#3700
b1001 $
b1001 (
0%
0)
b101110010 &
#3710
b101 +
b101 "
b10101 ,
1%
1)
b101110011 &
#3720
b1010 $
b1010 (
0%
0)
b101110100 &
#3730
b110 +
b110 "
b10110 ,
1%
1)
b101110101 &
#3740
b1011 $
b1011 (
0%
0)
b101110110 &
#3750
b111 +
b111 "
b10111 ,
1%
1)
b101110111 &
#3760
b1100 $
b1100 (
0%
0)
b101111000 &
#3770
b1000 +
b1000 "
b11000 ,
1%
1)
b101111001 &
#3780
b1101 $
b1101 (
0%
0)
b101111010 &
#3790
b1001 +
b1001 "
b11001 ,
1%
1)
b101111011 &
#3800
b1110 $
b1110 (
0%
0)
b101111100 &
#3810
b1010 +
b1010 "
b11010 ,
1%
1)
b101111101 &
#3820
b1111 $
b1111 (
0%
0)
b101111110 &
#3830
b1011 +
b1011 "
b11011 ,
1%
1)
b101111111 &
#3840
0*
0!
b1100 +
b1100 "
b1100 ,
b1100 #
b1100 '
b0 $
b0 (
0%
0)
b110000000 &
#3850
b1101 +
b1101 "
b1101 ,
1%
1)
b110000001 &
#3860
b1 $
b1 (
0%
0)
b110000010 &
#3870
b1110 +
b1110 "
b1110 ,
1%
1)
b110000011 &
#3880
b10 $
b10 (
0%
0)
b110000100 &
#3890
b1111 +
b1111 "
b1111 ,
1%
1)
b110000101 &
#3900
b11 $
b11 (
0%
0)
b110000110 &
#3910
1*
1!
b0 +
b0 "
b10000 ,
1%
1)
b110000111 &
#3920
b100 $
b100 (
0%
0)
b110001000 &
#3930
b1 +
b1 "
b10001 ,
1%
1)
b110001001 &
#3940
b101 $
b101 (
0%
0)
b110001010 &
#3950
b10 +
b10 "
b10010 ,
1%
1)
b110001011 &
#3960
b110 $
b110 (
0%
0)
b110001100 &
#3970
b11 +
b11 "
b10011 ,
1%
1)
b110001101 &
#3980
b111 $
b111 (
0%
0)
b110001110 &
#3990
b100 +
b100 "
b10100 ,
1%
1)
b110001111 &
#4000
b1000 $
b1000 (
0%
0)
b110010000 &
#4010
b101 +
b101 "
b10101 ,
1%
1)
b110010001 &
#4020
b1001 $
b1001 (
0%
0)
b110010010 &
#4030
b110 +
b110 "
b10110 ,
1%
1)
b110010011 &
#4040
b1010 $
b1010 (
0%
0)
b110010100 &
#4050
b111 +
b111 "
b10111 ,
1%
1)
b110010101 &
#4060
b1011 $
b1011 (
0%
0)
b110010110 &
#4070
b1000 +
b1000 "
b11000 ,
1%
1)
b110010111 &
#4080
b1100 $
b1100 (
0%
0)
b110011000 &
#4090
b1001 +
b1001 "
b11001 ,
1%
1)
b110011001 &
#4100
b1101 $
b1101 (
0%
0)
b110011010 &
#4110
b1010 +
b1010 "
b11010 ,
1%
1)
b110011011 &
#4120
b1110 $
b1110 (
0%
0)
b110011100 &
#4130
b1011 +
b1011 "
b11011 ,
1%
1)
b110011101 &
#4140
b1111 $
b1111 (
0%
0)
b110011110 &
#4150
b1100 +
b1100 "
b11100 ,
1%
1)
b110011111 &
#4160
0*
0!
b1101 +
b1101 "
b1101 ,
b1101 #
b1101 '
b0 $
b0 (
0%
0)
b110100000 &
#4170
b1110 +
b1110 "
b1110 ,
1%
1)
b110100001 &
#4180
b1 $
b1 (
0%
0)
b110100010 &
#4190
b1111 +
b1111 "
b1111 ,
1%
1)
b110100011 &
#4200
b10 $
b10 (
0%
0)
b110100100 &
#4210
1*
1!
b0 +
b0 "
b10000 ,
1%
1)
b110100101 &
#4220
b11 $
b11 (
0%
0)
b110100110 &
#4230
b1 +
b1 "
b10001 ,
1%
1)
b110100111 &
#4240
b100 $
b100 (
0%
0)
b110101000 &
#4250
b10 +
b10 "
b10010 ,
1%
1)
b110101001 &
#4260
b101 $
b101 (
0%
0)
b110101010 &
#4270
b11 +
b11 "
b10011 ,
1%
1)
b110101011 &
#4280
b110 $
b110 (
0%
0)
b110101100 &
#4290
b100 +
b100 "
b10100 ,
1%
1)
b110101101 &
#4300
b111 $
b111 (
0%
0)
b110101110 &
#4310
b101 +
b101 "
b10101 ,
1%
1)
b110101111 &
#4320
b1000 $
b1000 (
0%
0)
b110110000 &
#4330
b110 +
b110 "
b10110 ,
1%
1)
b110110001 &
#4340
b1001 $
b1001 (
0%
0)
b110110010 &
#4350
b111 +
b111 "
b10111 ,
1%
1)
b110110011 &
#4360
b1010 $
b1010 (
0%
0)
b110110100 &
