Intermediate_Projects/01_Parity_Gen_Check_System/Parity_Checker.v
//PARDON ME for using such a too long variable name its becoz i just wanted to tell and see myself when i again see it i dont have to optimize this code this is for learning and understanding puropse.


module Parity_Checker(input [2:0] a,
input p,output reg error );
reg computed_parity_after_fliiping_of_bits_due_to_noise;

always @(*) begin
    computed_parity_after_fliiping_of_bits_due_to_noise = a[2] ^ a[1] ^ a[0];
    if(computed_parity_after_fliiping_of_bits_due_to_noise!=p)begin
        error=1;//parity mismatche so error detected.
    end
    else
    begin
        error=0;
    end
end

 endmodule

Intermediate_Projects/1_Parity_Gen_Check_System/Parity_Generator.v
module Parity_Generator(input [2:0] a,
input parity_type,output reg p);

//Take 1 for odd parit; 0 for even parity adn which will be default. 

always @(*) begin

p = a[2] ^ a[1] ^ a[0];//default case as even paroty
if(parity_type == 1)
begin
    p=~p;
end
end



 endmodule

Intermediate_Projects/01_Parity_Gen_Check_System/Parity_System.v
module Parity_System(input [2:0] a,
input parity_type,
input [2:0] Checker_Data, output wire p,error);

Parity_Generator behav(.a(a),.parity_type(parity_type),.p(p));
Parity_Checker Behav(.a(Checker_Data),.p(p),.error(error));

endmodule

Intermediate_Projects/01_Parity_Gen_Check_System/testbench.v
`timescale 1ns/1ns

module testbench;
reg [2:0] a;
 reg parity_type;
 reg [2:0] Checker_Data;
 wire p,error;
integer i;
    Parity_System behav(.a(a),.parity_type(parity_type),.Checker_Data(Checker_Data),.p(p),.error(error));



 initial begin
    $dumpfile("Parity_System.vcd");
        $dumpvars(0, testbench);
    parity_type=0;//even parity 
    $display("\n----- EVEN PARITY CHECK -----");
    for(i=0;i<8;i=i+1)
    begin

        a=i[2:0];
        #5;
        Checker_Data=a; //no flipping happend 
        #5;
        //manually flipping 1 bit
$display("[EVEN] Input = %b, Parity = %b, Checker_Data = %b, Error = %b", a, p, Checker_Data, error);
        Checker_Data=a^3'b010;
        #5;
         //XOR is genrally used for flipping any bit in electronic likewise what we have to do is that whichever bit we have to flipi just write that bit as 1 and other as 0 and only that particular bit will be flliped
 $display("[EVEN] Input = %b, Parity = %b, Checker_Data (flipped) = %b, Error = %b", a, p, Checker_Data, error);end
parity_type=1;
  $display("\n----- ODD PARITY CHECK -----");
    for(i=0;i<8;i=i+1)
    begin

        a=i[2:0];
        #5;
        Checker_Data=a; 
        #5;
        $display("[ODD ] Input = %b, Parity = %b, Checker_Data = %b, Error = %b", a, p, Checker_Data, error);

        Checker_Data=a^3'b010;
        #5;
        $display("[ODD ] Input = %b, Parity = %b, Checker_Data (flipped) = %b, Error = %b", a, p, Checker_Data, error);
    end
 



$finish;



 end
endmodule

Intermediate_Projects/1_Parity_Gen_Check_System/Parity_System.vcd
$date
	Wed Jun 18 00:01:08 2025
$end
$version
	Icarus Verilog
$end
$timescale
	1ns
$end
$scope module testbench $end
$var wire 1 ! error $end
$var wire 1 " p $end
$var reg 3 # Checker_Data [2:0] $end
$var reg 3 $ a [2:0] $end
$var integer 32 % i [31:0] $end
$var reg 1 & parity_type $end
$scope module behav $end
$var wire 3 ' Checker_Data [2:0] $end
$var wire 3 ( a [2:0] $end
$var wire 1 ! error $end
$var wire 1 " p $end
$var wire 1 ) parity_type $end
$scope module behav $end
$var wire 3 * a [2:0] $end
$var wire 1 ) parity_type $end
$var reg 1 + p $end
$upscope $end
$scope module Behav $end
$var wire 3 , a [2:0] $end
$var wire 1 " p $end
$var reg 1 - computed_parity_after_fliiping_of_bits_due_to_noise $end
$var reg 1 . error $end
$upscope $end
$upscope $end
$upscope $end
$enddefinitions $end
#0
$dumpvars
0.
x-
bx ,
0+
b0 *
0)
b0 (
bx '
0&
b0 %
b0 $
bx #
0"
0!
$end
#5
0-
b0 #
b0 '
b0 ,
#10
1.
1!
1-
b10 #
b10 '
b10 ,
#15
0.
0!
1+
1"
b1 $
b1 (
b1 *
b1 %
#20
b1 #
b1 '
b1 ,
#25
1.
1!
0-
b11 #
b11 '
b11 ,
#30
b10 $
b10 (
b10 *
b10 %
#35
0.
0!
1-
b10 #
b10 '
b10 ,
#40
1.
1!
0-
b0 #
b0 '
b0 ,
#45
0.
0!
0+
0"
b11 $
b11 (
b11 *
b11 %
#50
b11 #
b11 '
b11 ,
#55
1.
1!
1-
b1 #
b1 '
b1 ,
#60
0.
0!
1+
1"
b100 $
b100 (
b100 *
b100 %
#65
b100 #
b100 '
b100 ,
#70
1.
1!
0-
b110 #
b110 '
b110 ,
#75
0.
0!
0+
0"
b101 $
b101 (
b101 *
b101 %
#80
b101 #
b101 '
b101 ,
#85
1.
1!
1-
b111 #
b111 '
b111 ,
#90
b110 $
b110 (
b110 *
b110 %
#95
0.
0!
0-
b110 #
b110 '
b110 ,
#100
1.
1!
1-
b100 #
b100 '
b100 ,
#105
0.
0!
1+
1"
b111 $
b111 (
b111 *
b111 %
#110
b111 #
b111 '
b111 ,
#115
1.
1!
0-
b101 #
b101 '
b101 ,
#120
1+
1"
b0 $
b0 (
b0 *
1&
1)
b0 %
#125
b0 #
b0 '
b0 ,
#130
0.
0!
1-
b10 #
b10 '
b10 ,
#135
1.
1!
0+
0"
b1 $
b1 (
b1 *
b1 %
#140
b1 #
b1 '
b1 ,
#145
0.
0!
0-
b11 #
b11 '
b11 ,
#150
0+
0"
b10 $
b10 (
b10 *
b10 %
#155
1.
1!
1-
b10 #
b10 '
b10 ,
#160
0.
0!
0-
b0 #
b0 '
b0 ,
#165
1.
1!
1+
1"
b11 $
b11 (
b11 *
b11 %
#170
b11 #
b11 '
b11 ,
#175
0.
0!
1-
b1 #
b1 '
b1 ,
#180
1.
1!
0+
0"
b100 $
b100 (
b100 *
b100 %
#185
b100 #
b100 '
b100 ,
#190
0.
0!
0-
b110 #
b110 '
b110 ,
#195
1.
1!
1+
1"
b101 $
b101 (
b101 *
b101 %
#200
b101 #
b101 '
b101 ,
#205
0.
0!
1-
b111 #
b111 '
b111 ,
#210
1+
1"
b110 $
b110 (
b110 *
b110 %
#215
1.
1!
0-
b110 #
b110 '
b110 ,
#220
0.
0!
1-
b100 #
b100 '
b100 ,
#225
1.
1!
0+
0"
b111 $
b111 (
b111 *
b111 %
#230
b111 #
b111 '
b111 ,
#235
0.
0!
0-
b101 #
b101 '
b101 ,
#240
b1000 %
