basic_projects/08_4to2_Encoder/encoder_4to2_behav.v
module encoder_4to2_behav(input i3,i2,i1,i0, output reg y1,y0);

always@(*)begin
    
casez({i3,i2,i1,i0})

4'b0000: begin  y1=1'bx;  y0=1'bx;end
4'b0001: begin  y1=0; y0=0; end
4'b001?: begin  y1=0; y0=1; end
4'b01??: begin  y1=1; y0=0; end
4'b1???: begin y1=1; y0=1;   end

default: begin y1=1'bx;  y0=1'bx; end

endcase

end




 endmodule

basic_projects/08_4to2_Encoder/testbench.v
`timescale 1ns/1ns

module testbench;
reg i3,i2,i1,i0;
wire y1,y0;
integer i;
encoder_4to2_behav behav(i3,i2,i1,i0,y1,y0);
initial begin
 $dumpfile("Encoder_4to2.vcd");
 $dumpvars(0,testbench);   

for(i=0;i<16;i=i+1)
begin
 {i3,i2,i1,i0}=i[3:0];
 #1;
 $display("i3=%b,i2=%b,i1=%b,i0=%b,y1=%b,y0=%b",i3,i2,i1,i0,y1,y0);
 #10;


end
$finish;
end



endmodule

basic_projects/08_4to2_Encoder/Encoder_4to2.vcd
$date
	Tue Jun 17 12:04:55 2025
$end
$version
	Icarus Verilog
$end
$timescale
	1ns
$end
$scope module testbench $end
$var wire 1 ! y0 $end
$var wire 1 " y1 $end
$var integer 32 # i [31:0] $end
$var reg 1 $ i0 $end
$var reg 1 % i1 $end
$var reg 1 & i2 $end
$var reg 1 ' i3 $end
$scope module behav $end
$var wire 1 ( i0 $end
$var wire 1 ) i1 $end
$var wire 1 * i2 $end
$var wire 1 + i3 $end
$var reg 1 , y0 $end
$var reg 1 - y1 $end
$upscope $end
$upscope $end
$enddefinitions $end
#0
$dumpvars
x-
x,
0+
0*
0)
0(
0'
0&
0%
0$
b0 #
x"
x!
$end
#11
0,
0!
0-
0"
1$
1(
b1 #
#22
1,
1!
1%
1)
0$
0(
b10 #
#33
1$
1(
b11 #
#44
0,
0!
1-
1"
1&
1*
0%
0)
0$
0(
b100 #
#55
1$
1(
b101 #
#66
1%
1)
0$
0(
b110 #
#77
1$
1(
b111 #
#88
1,
1!
1'
1+
0&
0*
0%
0)
0$
0(
b1000 #
#99
1$
1(
b1001 #
#110
1%
1)
0$
0(
b1010 #
#121
1$
1(
b1011 #
#132
1&
1*
0%
0)
0$
0(
b1100 #
#143
1$
1(
b1101 #
#154
1%
1)
0$
0(
b1110 #
#165
1$
1(
b1111 #
#176
b10000 #
