basic_projects/07_1to4_Demux/demux_1to4_behavioural.v
module  demux_1to4_behavioural(input i,s0,s1,e, output reg y0,y1,y2,y3);

always@(*)begin
if(e==1)begin
     
      y0 = 0;
    y1 = 0;
    y2 = 0;
    y3 = 0;
          case({s0,s1})
          2'b00: y0=i;
           2'b01: y1=i;
            2'b10: y2=i;
             2'b11: y3=i;
            
          endcase
end

end

endmodule

07_1to4_Demux/demux_1to4_gatelevel.v
module  demux_1to4_gatelevel(input i,s0,s1,e, output y0,y1,y2,y3);

wire s0_not,s1_not;

not g0(s0_not,s0);
not g1(s1_not,s1);

and g2(y0,i,e,s0_not,s1_not);
and g3(y1,i,e,s0_not,s1);
and g4(y2,i,e,s0,s1_not);
and g5(y3,i,e,s0,s1);

endmodule

basic_projects/07_1to4_Demux/testbench.v
`timescale 1ns/1ns

module testbench;
reg i,s0,s1,e;
wire y0_gate,y1_gate,y2_gate,y3_gate,y0_behav,y1_behav,y2_behav,y3_behav;
integer ip;
demux_1to4_gatelevel gate(.i(i),.s0(s0),.s1(s1),.e(e),.y0(y0_gate),.y1(y1_gate),.y2(y2_gate),.y3(y3_gate));
demux_1to4_behavioural behav(.i(i),.s0(s0),.s1(s1),.e(e),.y0(y0_behav),.y1(y1_behav),.y2(y2_behav),.y3(y3_behav));
initial begin

$dumpfile("Demux_1to4.vcd");
$dumpvars(0,testbench);

for(ip=0;ip<16;ip=ip+1)begin

{e,s1,s0,i}=ip[3:0];
#10;
$display("e=%b,s1=%b,s0=%b,i=%b,y0_gate=%b,y1_gate=%b,y2_gate=%b,y3_gate=%b,y0_behav=%b,y1_behav=%b,y2_behav=%b,y3_behav=%b",e,s1,s0,i,y0_gate,y1_gate,y2_gate,y3_gate,y0_behav,y1_behav,y2_behav,y3_behav);
end
$finish;
end

endmodule

basic_projects/07_1to4_Demux/Demux_1to4.vcd
$date
	Mon Jun 16 22:44:13 2025
$end
$version
	Icarus Verilog
$end
$timescale
	1ns
$end
$scope module testbench $end
$var wire 1 ! y0_behav $end
$var wire 1 " y0_gate $end
$var wire 1 # y1_behav $end
$var wire 1 $ y1_gate $end
$var wire 1 % y2_behav $end
$var wire 1 & y2_gate $end
$var wire 1 ' y3_behav $end
$var wire 1 ( y3_gate $end
$var reg 1 ) e $end
$var reg 1 * i $end
$var integer 32 + ip [31:0] $end
$var reg 1 , s0 $end
$var reg 1 - s1 $end
$scope module gate $end
$var wire 1 . e $end
$var wire 1 / i $end
$var wire 1 0 s0 $end
$var wire 1 1 s0_not $end
$var wire 1 2 s1 $end
$var wire 1 3 s1_not $end
$var wire 1 " y0 $end
$var wire 1 $ y1 $end
$var wire 1 & y2 $end
$var wire 1 ( y3 $end
$upscope $end
$scope module behav $end
$var wire 1 . e $end
$var wire 1 / i $end
$var wire 1 0 s0 $end
$var wire 1 2 s1 $end
$var reg 1 4 y0 $end
$var reg 1 5 y1 $end
$var reg 1 6 y2 $end
$var reg 1 7 y3 $end
$upscope $end
$upscope $end
$enddefinitions $end
#0
$dumpvars
x7
x6
x5
x4
13
02
11
00
0/
0.
0-
0,
b0 +
0*
0)
0(
x'
0&
x%
0$
x#
0"
x!
$end
#10
1*
1/
b1 +
#20
01
1,
10
0*
0/
b10 +
#30
1*
1/
b11 +
#40
03
11
1-
12
0,
00
0*
0/
b100 +
#50
1*
1/
b101 +
#60
01
1,
10
0*
0/
b110 +
#70
1*
1/
b111 +
#80
13
11
07
0'
06
0%
05
0#
04
0!
1)
1.
0-
02
0,
00
0*
0/
b1000 +
#90
1"
14
1!
1*
1/
b1001 +
#100
01
0"
04
0!
1,
10
0*
0/
b1010 +
#110
1&
16
1%
1*
1/
b1011 +
#120
03
11
0&
06
0%
1-
12
0,
00
0*
0/
b1100 +
#130
1$
15
1#
1*
1/
b1101 +
#140
01
0$
05
0#
1,
10
0*
0/
b1110 +
#150
1(
17
1'
1*
1/
b1111 +
#160
b10000 +
