basic_projects/06_1to2_Demux/demux_1to2_gatelevel.v
module demux_1to2_gatelevel (
    input i,e,s, output y0,y1);
wire s_not;
not g0(s_not,s);
and g1(y0,i,e,s_not);
and g2(y1,i,e,s);
endmodule

06_1to2_Demux/demux_1to2_behavioural.v
module demux_1to2_behavioural (
    input i,e,s, output reg y0,y1);
always@(*) begin
if(e==1)begin
case(s)
1'b0:  begin
     y0=i; y1=0;
end
1'b1: begin
     y0=0; y1=i;
end
endcase
end
else begin
y0=0;
y1=0;
end
end

    
endmodule

06_1to2_Demux/testbench.v
`timescale 1ns/1ns

module testbench;
reg i,s,e;
wire y0_behav,y1_behav,y0_gate,y1_gate;
integer ip;
demux_1to2_behavioural behav(.i(i),.s(s),.e(e),.y0(y0_behav),.y1(y1_behav));
demux_1to2_gatelevel gate(.i(i),.s(s),.e(e),.y0(y0_gate),.y1(y1_gate));
initial begin

$dumpfile("Demux_1to2.vcd");
$dumpvars(0,testbench);

for(ip=0;ip<8;ip=ip+1)
begin
    {e,s,i}=ip[2:0];
    #2
    $display("e=%b,s=%b,i=%b,y0_behav=%b,y1_behav=%b,y0_gate=%b,y1_gate=%b",e,s,i,y0_behav,y1_behav,y0_gate,y1_gate);
    #10;
end

$finish;
end








endmodule

06_1to2_Demux/Demux_1to2.vcd
$date
	Mon Jun 16 21:55:31 2025
$end
$version
	Icarus Verilog
$end
$timescale
	1ns
$end
$scope module testbench $end
$var wire 1 ! y0_behav $end
$var wire 1 " y0_gate $end
$var wire 1 # y1_behav $end
$var wire 1 $ y1_gate $end
$var reg 1 % e $end
$var reg 1 & i $end
$var integer 32 ' ip [31:0] $end
$var reg 1 ( s $end
$scope module behav $end
$var wire 1 ) e $end
$var wire 1 * i $end
$var wire 1 + s $end
$var reg 1 , y0 $end
$var reg 1 - y1 $end
$upscope $end
$scope module gate $end
$var wire 1 ) e $end
$var wire 1 * i $end
$var wire 1 + s $end
$var wire 1 . s_not $end
$var wire 1 " y0 $end
$var wire 1 $ y1 $end
$upscope $end
$upscope $end
$enddefinitions $end
#0
$dumpvars
1.
0-
0,
0+
0*
0)
0(
b0 '
0&
0%
0$
0#
0"
0!
$end
#12
1&
1*
b1 '
#24
0.
1(
1+
0&
0*
b10 '
#36
1&
1*
b11 '
#48
1.
1%
1)
0(
0+
0&
0*
b100 '
#60
1,
1!
1"
1&
1*
b101 '
#72
0.
0,
0!
0"
1(
1+
0&
0*
b110 '
#84
1-
1#
1$
1&
1*
b111 '
#96
b1000 '
